{"Fonction": ["Responsable Galeries Marchandes"], "Ville": ["ALCORCÓN - MADRID"], "Surface_hyper": ["14245"], "Statut": ["Ouvert"], "Telephone": ["+ 34 91 730 66 66"], "Site": ["ALCORCÓN"], "Mail": ["jc.garcia@alcampo.es"], "Nb_boutiques": ["40"], "Contact": ["José Carlos GARCIA"], "Surface_GLA": ["4298"], "Mobile": ["+ 34 606 432 723"]}
{"Fonction": ["Responsable Galeries Marchandes"], "Ville": ["Tainan"], "Surface_hyper": ["6560"], "Statut": ["Ouvert"], "Telephone": ["+ 88 82 27 95 28 88"], "Site": ["Anping"], "Mail": ["ga07@rt-mart.com.tw"], "Nb_boutiques": ["21"], "Contact": ["Roman LEE"], "Surface_GLA": ["969"], "Mobile": []}
{"Fonction": ["Responsable commercialisation"], "Ville": ["EPAGNY"], "Surface_hyper": ["10995"], "Statut": ["Extension - Rénovation"], "Telephone": ["04 13 60 06 07"], "Site": ["Annecy Grand Epagny "], "Mail": ["dbenisty@immochan.com"], "Nb_boutiques": ["61"], "Contact": ["Delphine BENISTY"], "Surface_GLA": ["20808"], "Mobile": ["06 03 23 39 64"]}
{"Fonction": ["Directrice régionale des centres commerciaux"], "Ville": ["Wuhu"], "Surface_hyper": ["9100"], "Statut": ["Ouvert"], "Telephone": ["+ (86) 021 25 05 21 32"], "Site": ["Anhui Ma Anshan"], "Mail": ["hui.fan@auchan.com.cn"], "Nb_boutiques": ["57"], "Contact": ["Hui FAN"], "Surface_GLA": ["6325"], "Mobile": []}
{"Fonction": ["Responsable commerciale"], "Ville": ["LA COURONNE"], "Surface_hyper": ["9600"], "Statut": ["Ouvert"], "Telephone": ["05 24 57 96 15"], "Site": ["Angoulême La Couronne "], "Mail": ["cparasie@immochan.com"], "Nb_boutiques": ["45"], "Contact": ["Charlotte PARASIE"], "Surface_GLA": ["6141"], "Mobile": ["06.21.35.45.91"]}
{"Fonction": ["Directrice régionale des centres commerciaux"], "Ville": ["Bengbu"], "Surface_hyper": [], "Statut": ["Ouvert"], "Telephone": ["+ (86) 021 25 05 21 32"], "Site": ["Anhui Bengbu"], "Mail": ["hui.fan@auchan.com.cn"], "Nb_boutiques": ["34"], "Contact": ["Hui FAN"], "Surface_GLA": ["5998"], "Mobile": []}
{"Fonction": [], "Ville": ["Setúbal"], "Surface_hyper": ["17000"], "Statut": ["Ouvert"], "Telephone": [], "Site": ["Alegro Setúbal"], "Mail": [], "Nb_boutiques": ["114"], "Contact": [], "Surface_GLA": ["27000"], "Mobile": []}
{"Fonction": ["Responsable commercialisation"], "Ville": ["Ancona"], "Surface_hyper": ["7706"], "Statut": ["Ouvert"], "Telephone": ["+ (02) 57 58 21 10"], "Site": ["Ancona"], "Mail": ["ettore.papponetti@gcispa.com"], "Nb_boutiques": ["41"], "Contact": ["Ettore PAPPONETTI"], "Surface_GLA": ["7644"], "Mobile": ["+ 3 93 35 27 75 93"]}
{"Fonction": [], "Ville": ["CASTELO BRANCO"], "Surface_hyper": ["6200"], "Statut": ["Ouvert"], "Telephone": [], "Site": ["Alegro Castelo Branco"], "Mail": [], "Nb_boutiques": ["55"], "Contact": [], "Surface_GLA": ["6830"], "Mobile": []}
{"Fonction": [], "Ville": ["CARNAXIDE"], "Surface_hyper": ["11960"], "Statut": ["Ouvert"], "Telephone": [], "Site": ["Alegro Alfragide"], "Mail": [], "Nb_boutiques": ["122"], "Contact": [], "Surface_GLA": ["11461"], "Mobile": []}
{"Fonction": ["Responsable commercialisation"], "Ville": ["ARRAS"], "Surface_hyper": ["6000"], "Statut": ["Ouvert"], "Telephone": ["03.62.53.79.41"], "Site": ["Arras "], "Mail": ["arousselot-doisy@immochan.com"], "Nb_boutiques": ["26"], "Contact": ["Angélique ROUSSELOT-DOISY"], "Surface_GLA": ["4000"], "Mobile": ["06.62.13.63.39"]}
{"Fonction": ["Responsable Commercialisation Regions "], "Ville": ["Krasnodar"], "Surface_hyper": [], "Statut": ["Ouvert"], "Telephone": ["+7 (903) 665 07 09"], "Site": ["АШАН АДЫГЕЯ (МЕГА КРАСНОДАР)"], "Mail": ["o.kazakov@auchan.ru"], "Nb_boutiques": ["21"], "Contact": ["Nadezhda Lazareva"], "Surface_GLA": ["1227"], "Mobile": []}
{"Fonction": ["Responsable Commercialisation Région de Moscou"], "Ville": ["Moscou"], "Surface_hyper": [], "Statut": ["Ouvert"], "Telephone": ["+7 (903) 665 10 39"], "Site": ["АШАН МАРФИНО "], "Mail": ["i.palaguina@auchan.ru"], "Nb_boutiques": ["62"], "Contact": ["Irina PALAGUINA"], "Surface_GLA": ["5148"], "Mobile": []}
{"Fonction": ["Responsable Commercialisation Region de Moscou"], "Ville": ["Moscou"], "Surface_hyper": [], "Statut": ["Ouvert"], "Telephone": [], "Site": ["АШАН МАРЬИНО  (ТЦ Л 153)"], "Mail": [], "Nb_boutiques": ["10"], "Contact": [], "Surface_GLA": ["413"], "Mobile": []}
{"Fonction": ["Responsable Commercialisation Region de Moscou"], "Ville": ["Moscou"], "Surface_hyper": [], "Statut": ["Ouvert"], "Telephone": [], "Site": ["АШАН БЕЛАЯ ДАЧА (Мега III)"], "Mail": [], "Nb_boutiques": ["23"], "Contact": [], "Surface_GLA": ["1235"], "Mobile": []}
{"Fonction": ["Responsable Commercialisation Regions "], "Ville": ["Krasnodar"], "Surface_hyper": [], "Statut": ["Ouvert"], "Telephone": ["+7 (903) 665 07 09"], "Site": ["АШАН СБС (ТЦ СБС)"], "Mail": ["o.kazakov@auchan.ru"], "Nb_boutiques": ["23"], "Contact": ["Nadezhda Lazareva"], "Surface_GLA": ["1387"], "Mobile": []}
{"Fonction": ["Responsable Commercialisation Region de Moscou"], "Ville": ["Moscou"], "Surface_hyper": [], "Statut": ["Ouvert"], "Telephone": [], "Site": ["АШАН ЛЕФОРТОВО, ТЦ ГОРОД II"], "Mail": [], "Nb_boutiques": ["21"], "Contact": [], "Surface_GLA": ["985"], "Mobile": []}
{"Fonction": ["Responsable Commercialisation Region de Moscou"], "Ville": ["Moscou"], "Surface_hyper": [], "Statut": ["Ouvert"], "Telephone": [], "Site": ["АШАН КОММУНАРКА (МЕГА ТЕПЛЫЙ СТАН)"], "Mail": [], "Nb_boutiques": ["21"], "Contact": [], "Surface_GLA": ["416"], "Mobile": []}
{"Fonction": ["Responsable Commercialisation Région de Moscou"], "Ville": ["Moscou"], "Surface_hyper": [], "Statut": ["Ouvert"], "Telephone": ["+7 (903) 665 10 39"], "Site": ["АШАН АЛТУФЬЕВО"], "Mail": ["i.palaguina@auchan.ru"], "Nb_boutiques": ["59"], "Contact": ["Irina PALAGUINA"], "Surface_GLA": ["6663"], "Mobile": []}
{"Fonction": ["Responsable Commercialisation Regions "], "Ville": ["Ekaterinburg "], "Surface_hyper": [], "Statut": ["Ouvert"], "Telephone": ["+7 (903) 665 07 09"], "Site": ["АШАН ЕКАТЕРИНБУРГ (\"МЕГА\" ЕКАТЕРИНБУРГ)"], "Mail": ["o.kazakov@auchan.ru"], "Nb_boutiques": ["19"], "Contact": ["Nadezhda Lazareva"], "Surface_GLA": ["1232"], "Mobile": []}
{"Fonction": ["Responsable Commercialisation Région de Moscou"], "Ville": ["Moscou"], "Surface_hyper": [], "Statut": ["Ouvert"], "Telephone": [], "Site": ["Мытищи"], "Mail": [], "Nb_boutiques": ["51"], "Contact": [], "Surface_GLA": ["4546"], "Mobile": []}
{"Fonction": ["Responsable commercialisation"], "Ville": ["AVIGNON "], "Surface_hyper": ["10007"], "Statut": ["Ouvert"], "Telephone": ["04 13 60 06 07"], "Site": ["Avignon Mistral 7"], "Mail": ["dbenisty@immochan.com"], "Nb_boutiques": ["73"], "Contact": ["Delphine BENISTY"], "Surface_GLA": ["11460"], "Mobile": ["06 03 23 39 64"]}
{"Fonction": ["Responsable Galeries Marchandes"], "Ville": ["Taoyuan"], "Surface_hyper": ["8956"], "Statut": ["Ouvert"], "Telephone": ["+ 88 82 27 95 28 88"], "Site": ["Bade"], "Mail": ["ga08@rt-mart.com.tw"], "Nb_boutiques": ["20"], "Contact": ["Rick HSU"], "Surface_GLA": ["1144"], "Mobile": []}
{"Fonction": ["Directrice Commerciale"], "Ville": ["Warszawa - Łomianki"], "Surface_hyper": ["12300"], "Statut": ["Ouvert"], "Telephone": [], "Site": ["Auchan Łomianki"], "Mail": [], "Nb_boutiques": ["90"], "Contact": [], "Surface_GLA": ["16400"], "Mobile": []}
{"Fonction": ["Responsable Commercialisation Regions "], "Ville": ["Rostov-na-Donu"], "Surface_hyper": [], "Statut": ["Ouvert"], "Telephone": ["+7 (903) 665 07 09"], "Site": ["ТЦ АШАН ОРБИТАЛЬНАЯ "], "Mail": ["o.kazakov@auchan.ru"], "Nb_boutiques": ["21"], "Contact": ["Nadezhda Lazareva"], "Surface_GLA": ["1534"], "Mobile": []}
{"Fonction": ["Responsable Commercialisation Régions "], "Ville": ["Samara"], "Surface_hyper": [], "Statut": ["Ouvert"], "Telephone": ["+7 (903) 665 07 09"], "Site": ["АШАН САМАРА (МЕГА САМАРА)"], "Mail": ["o.kazakov@auchan.ru"], "Nb_boutiques": ["18"], "Contact": ["Nadezhda Lazareva"], "Surface_GLA": ["1133"], "Mobile": []}
{"Fonction": ["Responsable commercialisation"], "Ville": ["LE PONTET"], "Surface_hyper": ["18000"], "Statut": ["Extension - Rénovation"], "Telephone": ["04.13.60.06.06"], "Site": ["Avignon Nord"], "Mail": ["clancelot@immochan.com"], "Nb_boutiques": ["114"], "Contact": ["Céline LANCELOT"], "Surface_GLA": ["39827"], "Mobile": ["06 28 96 41 51"]}
{"Fonction": ["Directrice Commerciale"], "Ville": ["Warszawa - Piaseczno "], "Surface_hyper": ["13878"], "Statut": ["Extension - Rénovation"], "Telephone": ["+48 22 209 86 23"], "Site": ["Galeria Piaseczno"], "Mail": ["awalentek@immochan.com"], "Nb_boutiques": ["46"], "Contact": ["Ada Walentek"], "Surface_GLA": ["7257"], "Mobile": []}
{"Fonction": ["Responsable Commercialisation Regions "], "Ville": ["Novosibirsk"], "Surface_hyper": [], "Statut": ["Ouvert"], "Telephone": ["+7 (903) 665 07 09"], "Site": ["АШАН НОВОСИБИРСК (МЕГА НОВОСИБИРСК)"], "Mail": ["o.kazakov@auchan.ru"], "Nb_boutiques": ["19"], "Contact": ["Nadezhda Lazareva"], "Surface_GLA": ["1254"], "Mobile": []}
{"Fonction": ["Responsable commercialisation"], "Ville": ["Modugno Bari"], "Surface_hyper": ["8987"], "Statut": ["Ouvert"], "Telephone": ["+ (02) 57 58 21 10"], "Site": ["Bari Modugno"], "Mail": ["ettore.papponetti@gcispa.com"], "Nb_boutiques": ["24"], "Contact": ["Ettore PAPPONETTI"], "Surface_GLA": ["4246"], "Mobile": ["+ 3 93 35 27 75 93"]}
{"Fonction": ["Chargée de commercialisation"], "Ville": ["BIGANOS"], "Surface_hyper": ["7000"], "Statut": ["Ouvert"], "Telephone": ["05 24 57 96 15"], "Site": ["Biganos"], "Mail": ["cparasie@immochan.com"], "Nb_boutiques": ["46"], "Contact": ["Charlotte PARASIE"], "Surface_GLA": ["3600"], "Mobile": ["06.21.35.45.91"]}
{"Fonction": ["Responsable commercialisation"], "Ville": ["VINEUIL"], "Surface_hyper": ["9400"], "Statut": ["Ouvert"], "Telephone": ["05.24.57.96.42"], "Site": ["Blois-Vineuil"], "Mail": ["tnguyen@immochan.com"], "Nb_boutiques": ["53"], "Contact": ["Tuan NGUYEN"], "Surface_GLA": ["8000"], "Mobile": ["06.33.45.38.02"]}
{"Fonction": [], "Ville": ["BESSONCOURT"], "Surface_hyper": ["4188"], "Statut": ["Ouvert"], "Telephone": ["01.77.51.00.69"], "Site": ["Belfort Bessoncourt "], "Mail": ["ngauthier@immochan.com"], "Nb_boutiques": ["18"], "Contact": ["Nathalie GAUTHIER"], "Surface_GLA": ["9200"], "Mobile": ["06.23.34.44.40"]}
{"Fonction": ["Responsable Galeries Marchandes"], "Ville": ["New Taipei"], "Surface_hyper": ["4944"], "Statut": ["Ouvert"], "Telephone": ["+ 88 82 27 95 28 88"], "Site": ["Bitan"], "Mail": ["ga06@rt-mart.com.tw"], "Nb_boutiques": ["8"], "Contact": ["Pat HO"], "Surface_GLA": ["126"], "Mobile": []}
{"Fonction": ["Directeur de commercialisation"], "Ville": ["Bergamo"], "Surface_hyper": ["9522"], "Statut": ["Ouvert"], "Telephone": ["+39 02 57 58 48 64"], "Site": ["Bergamo"], "Mail": ["giampiero.dimaio@gcispa.com"], "Nb_boutiques": ["20"], "Contact": ["Giampiero DI MAIO"], "Surface_GLA": ["1829"], "Mobile": []}
{"Fonction": ["Directrice Commerciale"], "Ville": ["Białystok"], "Surface_hyper": ["13000"], "Statut": ["Ouvert"], "Telephone": ["+48 22 209 86 23"], "Site": ["Auchan Białystok "], "Mail": ["awalentek@immochan.com"], "Nb_boutiques": ["56"], "Contact": ["Ada Walentek"], "Surface_GLA": ["7400"], "Mobile": []}
{"Fonction": ["Directrice régionale des centres commerciaux"], "Ville": ["Beijing"], "Surface_hyper": ["9061"], "Statut": ["Ouvert"], "Telephone": [], "Site": ["Beijing 4 Chaoyang"], "Mail": ["zhaoxu.ju@auchan.com.cn"], "Nb_boutiques": ["74"], "Contact": ["Zhaoxu JU"], "Surface_GLA": ["3652"], "Mobile": []}
{"Fonction": ["Directrice régionale des centres commerciaux"], "Ville": ["Beijing"], "Surface_hyper": ["11000"], "Statut": ["Ouvert"], "Telephone": [], "Site": ["Beijing 2 Kexing"], "Mail": ["zhaoxu.ju@auchan.com.cn"], "Nb_boutiques": ["41"], "Contact": ["Zhaoxu JU"], "Surface_GLA": ["4134"], "Mobile": []}
{"Fonction": ["Directrice régionale des centres commerciaux"], "Ville": ["Beijing"], "Surface_hyper": ["10366"], "Statut": ["Ouvert"], "Telephone": [], "Site": ["Beijing 1 Golden Season"], "Mail": ["zhaoxu.ju@auchan.com.cn"], "Nb_boutiques": ["167"], "Contact": ["Zhaoxu JU"], "Surface_GLA": ["1119"], "Mobile": []}
{"Fonction": ["Responsable  commercialisation"], "Ville": ["MELUN"], "Surface_hyper": ["14000"], "Statut": ["Ouvert"], "Telephone": ["01 47 62 61 68"], "Site": ["Bois Senart "], "Mail": ["fmoreau@immochan.com"], "Nb_boutiques": ["100"], "Contact": ["Frédérike  MOREAU"], "Surface_GLA": ["42000"], "Mobile": ["06 29 75 75 17"]}
{"Fonction": ["Responsable commercialisation"], "Ville": ["Cagliari"], "Surface_hyper": ["7762"], "Statut": ["Ouvert"], "Telephone": ["+ (02) 57 58 21 10"], "Site": ["Cagliari Marconi"], "Mail": ["ettore.papponetti@gcispa.com"], "Nb_boutiques": ["43"], "Contact": ["Ettore PAPPONETTI"], "Surface_GLA": ["10270"], "Mobile": ["+ 3 93 35 27 75 93"]}
{"Fonction": ["Directeur de commercialisation"], "Ville": ["Bussolengo"], "Surface_hyper": ["9000"], "Statut": ["Extension - Rénovation"], "Telephone": ["+39 02 57 58 48 64"], "Site": ["Bussolengo"], "Mail": ["giampiero.dimaio@gcispa.com"], "Nb_boutiques": ["35"], "Contact": ["Giampiero DI MAIO"], "Surface_GLA": ["7956"], "Mobile": []}
{"Fonction": ["Responsable de commercialisation"], "Ville": ["Budakalász"], "Surface_hyper": ["12621"], "Statut": ["Ouvert"], "Telephone": [], "Site": ["Budakalász"], "Mail": [], "Nb_boutiques": ["35"], "Contact": [], "Surface_GLA": ["3553"], "Mobile": []}
{"Fonction": ["Responsable de commercialisation"], "Ville": ["Budaörs"], "Surface_hyper": ["16382"], "Statut": ["Ouvert"], "Telephone": [], "Site": ["Budaörs"], "Mail": [], "Nb_boutiques": ["60"], "Contact": [], "Surface_GLA": ["6220"], "Mobile": []}
{"Fonction": ["Responsable commercialisation"], "Ville": ["BRETIGNY SUR ORGE "], "Surface_hyper": ["12000"], "Statut": ["Extension - Rénovation"], "Telephone": [], "Site": ["Brétigny/Orge Maison Neuve "], "Mail": ["sauneau@immochan.com"], "Nb_boutiques": ["70"], "Contact": ["Stéphanie Auneau"], "Surface_GLA": ["11200"], "Mobile": ["06.72.04.66.89"]}
{"Fonction": ["Responsable commercialisation"], "Ville": ["Brindisi"], "Surface_hyper": ["8019"], "Statut": ["Ouvert"], "Telephone": ["+ (02) 57 58 21 10"], "Site": ["Brindisi Mesagne"], "Mail": ["ettore.papponetti@gcispa.com"], "Nb_boutiques": ["59"], "Contact": ["Ettore PAPPONETTI"], "Surface_GLA": ["13000"], "Mobile": ["+ 3 93 35 27 75 93"]}
{"Fonction": ["Responsable  commercialisation"], "Ville": ["SAINT-MARTIN-BOULOGNE"], "Surface_hyper": ["14690"], "Statut": ["Ouvert"], "Telephone": ["06.24.98.22.01"], "Site": ["Boulogne-sur-Mer "], "Mail": ["cbarrois@immochan.com"], "Nb_boutiques": ["44"], "Contact": ["Christophe BARROIS"], "Surface_GLA": ["7100"], "Mobile": []}
{"Fonction": ["Chargée de commercialisation"], "Ville": ["BOULIAC"], "Surface_hyper": ["11390"], "Statut": ["Extension - Rénovation"], "Telephone": ["05 24 57 96 12"], "Site": ["Bouliac"], "Mail": ["cvidal@immochan.com"], "Nb_boutiques": ["32"], "Contact": ["Charlotte VIDAL"], "Surface_GLA": ["4540"], "Mobile": ["06 13 57 67 41"]}
{"Fonction": ["Responsable commercial"], "Ville": ["Bordeaux "], "Surface_hyper": ["18000"], "Statut": ["Extension - Rénovation"], "Telephone": ["05.24.57.96.42"], "Site": ["Bordeaux Lac "], "Mail": ["tnguyen@immochan.com"], "Nb_boutiques": ["118"], "Contact": ["Tuan NGUYEN"], "Surface_GLA": ["26000"], "Mobile": ["06.33.45.38.02"]}
{"Fonction": ["Responsable commercialisation"], "Ville": ["Cagliari"], "Surface_hyper": ["7055"], "Statut": ["Ouvert"], "Telephone": ["+ (02) 57 58 21 10"], "Site": ["Cagliari Santa Gilla"], "Mail": ["ettore.papponetti@gcispa.com"], "Nb_boutiques": ["42"], "Contact": ["Ettore PAPPONETTI"], "Surface_GLA": ["10384"], "Mobile": ["+ 3 93 35 27 75 93"]}
{"Fonction": ["Responsable commercialisation"], "Ville": ["Villanova di Cepagatti"], "Surface_hyper": ["7452"], "Statut": ["Ouvert"], "Telephone": ["+ (02) 57 58 21 10"], "Site": ["Cepagatti"], "Mail": ["ettore.papponetti@gcispa.com"], "Nb_boutiques": ["34"], "Contact": ["Ettore PAPPONETTI"], "Surface_GLA": ["17617"], "Mobile": ["+ 3 93 35 27 75 93"]}
{"Fonction": ["Responsable commercialisation"], "Ville": ["Casamassima"], "Surface_hyper": ["14474"], "Statut": ["Ouvert"], "Telephone": ["+ (02) 57 58 21 10"], "Site": ["Casamassima"], "Mail": ["ettore.papponetti@gcispa.com"], "Nb_boutiques": ["103"], "Contact": ["Ettore PAPPONETTI"], "Surface_GLA": ["29786"], "Mobile": ["+ 3 93 35 27 75 93"]}
{"Fonction": ["Responsable commercialisation"], "Ville": ["Catania Misterbianco"], "Surface_hyper": ["7735"], "Statut": ["Ouvert"], "Telephone": ["+ (02) 57 58 21 10"], "Site": ["Catania Misterbianco"], "Mail": ["ettore.papponetti@gcispa.com"], "Nb_boutiques": ["17"], "Contact": ["Ettore PAPPONETTI"], "Surface_GLA": ["1474"], "Mobile": ["+ 3 93 35 27 75 93"]}
{"Fonction": ["Responsable commercialisation"], "Ville": ["Catania"], "Surface_hyper": ["6000"], "Statut": ["Ouvert"], "Telephone": ["+ (02) 57 58 21 10"], "Site": ["Catania La Rena"], "Mail": ["ettore.papponetti@gcispa.com"], "Nb_boutiques": ["13"], "Contact": ["Ettore PAPPONETTI"], "Surface_GLA": ["2167"], "Mobile": ["+ 3 93 35 27 75 93"]}
{"Fonction": ["Directrice Commerciale"], "Ville": ["Warszawa - Góraszka"], "Surface_hyper": ["16000"], "Statut": ["Nouveaux projets"], "Telephone": ["+48 22 209 86 23"], "Site": ["Centrum Góraszka Kolorowe Życie"], "Mail": ["awalentek@immochan.com"], "Nb_boutiques": ["220"], "Contact": ["Ada Walentek"], "Surface_GLA": ["84000"], "Mobile": []}
{"Fonction": ["Responsable commercialisation"], "Ville": ["CASTRES"], "Surface_hyper": ["7930"], "Statut": ["Extension - Rénovation"], "Telephone": ["05 24 57 96 12"], "Site": ["Castres"], "Mail": ["cvidal@immochan.com"], "Nb_boutiques": ["25"], "Contact": ["Charlotte VIDAL"], "Surface_GLA": ["5096"], "Mobile": ["06 13 57 67 41"]}
{"Fonction": ["Responsable commercialisation"], "Ville": ["Rome"], "Surface_hyper": ["6013"], "Statut": ["Ouvert"], "Telephone": ["+ (02) 57 58 21 10"], "Site": ["Casalbertone"], "Mail": ["ettore.papponetti@gcispa.com"], "Nb_boutiques": ["52"], "Contact": ["Ettore PAPPONETTI"], "Surface_GLA": ["8019"], "Mobile": ["+ 3 93 35 27 75 93"]}
{"Fonction": ["Responsable  commercialisation"], "Ville": ["ESCAUDOEUVRES"], "Surface_hyper": ["8700"], "Statut": ["Ouvert"], "Telephone": ["06.24.98.22.01"], "Site": ["Cambrai"], "Mail": ["cbarrois@immochan.com"], "Nb_boutiques": ["28"], "Contact": ["Christophe BARROIS"], "Surface_GLA": ["3300"], "Mobile": []}
{"Fonction": [], "Ville": ["BURGOS"], "Surface_hyper": ["7618"], "Statut": ["Ouvert"], "Telephone": [], "Site": ["CAMINO DE LA PLATA"], "Mail": [], "Nb_boutiques": ["55"], "Contact": [], "Surface_GLA": ["6589"], "Mobile": []}
{"Fonction": ["Directeur de commercialisation"], "Ville": ["Cesano Boscone"], "Surface_hyper": ["9100"], "Statut": ["Ouvert"], "Telephone": ["+39 02 57 58 48 64"], "Site": ["Cesano Boscone"], "Mail": ["giampiero.dimaio@gcispa.com"], "Nb_boutiques": ["53"], "Contact": ["Giampiero DI MAIO"], "Surface_GLA": ["8639"], "Mobile": []}
{"Fonction": ["Responsable  commercialisation"], "Ville": ["CHATEAUROUX "], "Surface_hyper": [], "Statut": ["Ouvert"], "Telephone": ["05 24 57 96 12"], "Site": ["Châteauroux"], "Mail": ["cvidal@immochan.com"], "Nb_boutiques": [], "Contact": ["Charlotte VIDAL"], "Surface_GLA": ["2600"], "Mobile": ["06 13 57 67 41"]}
{"Fonction": ["Directrice régionale des centres commerciaux"], "Ville": ["Chengdu"], "Surface_hyper": ["9269"], "Statut": ["Ouvert"], "Telephone": [], "Site": ["Chengdu - Huayang"], "Mail": ["zhaoxu.ju@auchan.com.cn"], "Nb_boutiques": ["61"], "Contact": ["Zhaoxu JU"], "Surface_GLA": ["5740"], "Mobile": []}
{"Fonction": ["Directrice régionale des centres commerciaux"], "Ville": ["Chengdu"], "Surface_hyper": ["8253"], "Statut": ["Ouvert"], "Telephone": [], "Site": ["Chengdu 1 Jinniu"], "Mail": ["zhaoxu.ju@auchan.com.cn"], "Nb_boutiques": ["40"], "Contact": ["Zhaoxu JU"], "Surface_GLA": ["3713"], "Mobile": []}
{"Fonction": ["Responsable commercialisation"], "Ville": ["CHATELLERAULT"], "Surface_hyper": ["8000"], "Statut": ["Ouvert"], "Telephone": ["05 24 57 96 12"], "Site": ["Châtellerault"], "Mail": ["cvidal@immochan.com"], "Nb_boutiques": ["34"], "Contact": ["Charlotte VIDAL"], "Surface_GLA": ["6000"], "Mobile": ["06 13 57 67 41"]}
{"Fonction": ["Directeur régional des centres commerciaux"], "Ville": ["Jiangsu"], "Surface_hyper": ["8640"], "Statut": ["Ouvert"], "Telephone": [], "Site": ["Changzhou 2 Wuxing"], "Mail": ["honghui.zhou@auchan.com.cn"], "Nb_boutiques": ["56"], "Contact": ["Honghui ZHOU"], "Surface_GLA": ["4251"], "Mobile": []}
{"Fonction": ["Directeur régional des centres commerciaux"], "Ville": ["Jiangsu "], "Surface_hyper": ["13300"], "Statut": ["Ouvert"], "Telephone": [], "Site": ["Changzhou 3 Yongning"], "Mail": ["honghui.zhou@auchan.com.cn"], "Nb_boutiques": ["103"], "Contact": ["Honghui ZHOU"], "Surface_GLA": ["14084"], "Mobile": []}
{"Fonction": ["Directeur régional des centres commerciaux"], "Ville": ["Jiangsu"], "Surface_hyper": ["9150"], "Statut": ["Ouvert"], "Telephone": [], "Site": ["Changzhou 1 Lanling"], "Mail": ["honghui.zhou@auchan.com.cn"], "Nb_boutiques": ["80"], "Contact": ["Honghui ZHOU"], "Surface_GLA": ["7838"], "Mobile": []}
{"Fonction": ["Directeur régional des centres commerciaux"], "Ville": ["Jiangsu"], "Surface_hyper": ["7801"], "Statut": ["Ouvert"], "Telephone": [], "Site": ["Changshu Zhujiang"], "Mail": ["honghui.zhou@auchan.com.cn"], "Nb_boutiques": ["55"], "Contact": ["Honghui ZHOU"], "Surface_GLA": ["6816"], "Mobile": []}
{"Fonction": ["Directeur régional des centres commerciaux"], "Ville": ["Changshu"], "Surface_hyper": ["8000"], "Statut": ["Ouvert"], "Telephone": [], "Site": ["Changshu Huanghe"], "Mail": ["honghui.zhou@auchan.com.cn"], "Nb_boutiques": ["60"], "Contact": ["Honghui ZHOU"], "Surface_GLA": ["4573"], "Mobile": []}
{"Fonction": ["Responsable Galeries Marchandes"], "Ville": ["Comté de Tainan"], "Surface_hyper": ["5892"], "Statut": ["Ouvert"], "Telephone": ["+ 88 82 27 95 28 88"], "Site": ["Chiali "], "Mail": ["ga07@rt-mart.com.tw"], "Nb_boutiques": ["8"], "Contact": ["Roman LEE"], "Surface_GLA": ["229"], "Mobile": []}
{"Fonction": ["Responsable commercialisation"], "Ville": ["Rome"], "Surface_hyper": ["5690"], "Statut": ["Ouvert"], "Telephone": ["+ (02) 57 58 21 10"], "Site": ["Collatina"], "Mail": ["ettore.papponetti@gcispa.com"], "Nb_boutiques": ["8"], "Contact": ["Ettore PAPPONETTI"], "Surface_GLA": ["375"], "Mobile": ["+ 3 93 35 27 75 93"]}
{"Fonction": ["Responsable Galeries Marchandes"], "Ville": ["HsinChu"], "Surface_hyper": ["9572"], "Statut": ["Ouvert"], "Telephone": ["+ 88 82 27 95 28 88"], "Site": ["Chungshiao"], "Mail": ["ga08@rt-mart.com.tw"], "Nb_boutiques": ["43"], "Contact": ["Rick HSU"], "Surface_GLA": ["4273"], "Mobile": []}
{"Fonction": ["Responsable Galeries Marchandes"], "Ville": ["Taipei"], "Surface_hyper": ["6486"], "Statut": ["Ouvert"], "Telephone": ["+ 88 82 27 95 28 88"], "Site": ["City Link"], "Mail": ["ga06@rt-mart.com.tw"], "Nb_boutiques": ["9"], "Contact": ["Pat HO"], "Surface_GLA": ["754"], "Mobile": []}
{"Fonction": ["Directeur de commercialisation"], "Ville": ["Cinisello Balsamo"], "Surface_hyper": ["12664"], "Statut": ["Ouvert"], "Telephone": ["+39 02 57 58 48 64"], "Site": ["Cinisello Balsamo"], "Mail": ["giampiero.dimaio@gcispa.com"], "Nb_boutiques": ["104"], "Contact": ["Giampiero DI MAIO"], "Surface_GLA": ["22305"], "Mobile": []}
{"Fonction": ["Responsable Galeries Marchandes"], "Ville": ["Taichung 404"], "Surface_hyper": ["9590"], "Statut": ["Ouvert"], "Telephone": ["+ 88 82 27 95 28 88"], "Site": ["Chungming"], "Mail": ["ga08@rt-mart.com.tw"], "Nb_boutiques": ["27"], "Contact": ["Rick HSU"], "Surface_GLA": ["1303"], "Mobile": []}
{"Fonction": ["Responsable commerciale "], "Ville": ["Cognac"], "Surface_hyper": ["6206"], "Statut": ["Ouvert"], "Telephone": [], "Site": ["COGNAC "], "Mail": [""], "Nb_boutiques": ["37"], "Contact": ["PARASIE  Charlotte "], "Surface_GLA": ["4000"], "Mobile": []}
{"Fonction": ["Responsable Galeries Marchandes"], "Ville": ["Comté de Taoyuan"], "Surface_hyper": ["8947"], "Statut": ["Ouvert"], "Telephone": ["+ 88 82 27 95 28 88"], "Site": ["Chungli"], "Mail": ["ga08@rt-mart.com.tw"], "Nb_boutiques": ["40"], "Contact": ["Rick HSU"], "Surface_GLA": ["3848"], "Mobile": []}
{"Fonction": ["Responsable Galeries Marchandes"], "Ville": ["New Taipei"], "Surface_hyper": ["6533"], "Statut": ["Ouvert"], "Telephone": ["+ 88 82 27 95 28 88"], "Site": ["Chungho"], "Mail": ["ga06@rt-mart.com.tw"], "Nb_boutiques": ["20"], "Contact": ["Pat HO"], "Surface_GLA": ["1163"], "Mobile": []}
{"Fonction": ["Responsable Galeries Marchandes"], "Ville": ["Chiayi"], "Surface_hyper": ["10590"], "Statut": ["Ouvert"], "Telephone": ["+ 88 82 27 95 28 88"], "Site": ["Chiayi "], "Mail": ["ga07@rt-mart.com.tw"], "Nb_boutiques": ["30"], "Contact": ["Roman LEE"], "Surface_GLA": ["2579"], "Mobile": []}
{"Fonction": ["Directeur de commercialisation"], "Ville": ["Concesio Brescia"], "Surface_hyper": ["8300"], "Statut": ["Ouvert"], "Telephone": ["+39 02 57 58 48 64"], "Site": ["Concesio"], "Mail": ["giampiero.dimaio@gcispa.com"], "Nb_boutiques": ["14"], "Contact": ["Giampiero DI MAIO"], "Surface_GLA": ["2525"], "Mobile": []}
{"Fonction": ["Responsable  commercialisation"], "Ville": ["DIEPPE"], "Surface_hyper": ["11300"], "Statut": ["Ouvert"], "Telephone": ["06.24.98.22.01"], "Site": ["Dieppe"], "Mail": ["cbarrois@immochan.com"], "Nb_boutiques": ["39"], "Contact": ["Christophe BARROIS"], "Surface_GLA": ["3400"], "Mobile": []}
{"Fonction": ["Directeur de commercialisation"], "Ville": ["Cuneo"], "Surface_hyper": ["7500"], "Statut": ["Ouvert"], "Telephone": ["+39 02 57 58 48 64"], "Site": ["Cuneo"], "Mail": ["giampiero.dimaio@gcispa.com"], "Nb_boutiques": ["42"], "Contact": ["Giampiero DI MAIO"], "Surface_GLA": ["7671"], "Mobile": []}
{"Fonction": ["Directeur régional des centres commerciaux"], "Ville": ["Danyang"], "Surface_hyper": ["10056"], "Statut": ["Ouvert"], "Telephone": [], "Site": ["Danyang"], "Mail": ["honghui.zhou@auchan.com.cn"], "Nb_boutiques": ["66"], "Contact": ["Honghui ZHOU"], "Surface_GLA": ["6427"], "Mobile": []}
{"Fonction": ["Responsable de commercialisation"], "Ville": ["Debrecen"], "Surface_hyper": ["10972"], "Statut": ["Ouvert"], "Telephone": ["+ 36 18 87 45 25"], "Site": ["Debrecen"], "Mail": ["h.cziegler@auchan.hu"], "Nb_boutiques": ["28"], "Contact": ["Helga CZIEGLER"], "Surface_GLA": ["2905"], "Mobile": ["+ 363 04 88 16 75"]}
{"Fonction": ["Responsable de commercialisation"], "Ville": ["Csömör"], "Surface_hyper": ["14404"], "Statut": ["Ouvert"], "Telephone": ["+ 36 18 87 45 33"], "Site": ["Csömör"], "Mail": ["o.baki@auchan.hu"], "Nb_boutiques": ["27"], "Contact": ["Orsolya BAKI"], "Surface_GLA": ["1490"], "Mobile": ["+ 363 02 51 94 09"]}
{"Fonction": ["Responsable Galeries Marchandes"], "Ville": ["CUENCA"], "Surface_hyper": ["4327"], "Statut": ["Ouvert"], "Telephone": ["+ 34 91 730 66 66"], "Site": ["CUENCA"], "Mail": ["angel.garcia@alcampo.es"], "Nb_boutiques": ["15"], "Contact": ["Angel GARCIA"], "Surface_GLA": ["1282"], "Mobile": ["+ 34 618 342 095"]}
{"Fonction": ["Directeur Commercial"], "Ville": ["BUCAREST"], "Surface_hyper": ["4800"], "Statut": ["Ouvert"], "Telephone": [], "Site": ["Crângași"], "Mail": ["oiancu@immochan.com"], "Nb_boutiques": ["27"], "Contact": ["Ofelia IANCU"], "Surface_GLA": ["2400"], "Mobile": []}
{"Fonction": ["Directrice Commercialisation"], "Ville": ["BRASOV"], "Surface_hyper": ["13300"], "Statut": ["Ouvert"], "Telephone": [], "Site": ["Coresi"], "Mail": ["ampop@immochan.com"], "Nb_boutiques": ["130"], "Contact": ["Anca Pop"], "Surface_GLA": ["45300"], "Mobile": ["+ 40 748 05 12 74"]}
{"Fonction": ["Responsable des centres Canton"], "Ville": ["Dongguan"], "Surface_hyper": [], "Statut": ["Ouvert"], "Telephone": ["+ (86) 020 38 08 32 50  "], "Site": ["Dongguan - Liaobu"], "Mail": ["jinquan.wang@auchan.com.cn"], "Nb_boutiques": ["44"], "Contact": ["Jingquan WANG"], "Surface_GLA": ["9102"], "Mobile": []}
{"Fonction": ["Responsable commerciale"], "Ville": ["FACHES-THUMESNIL"], "Surface_hyper": ["12700"], "Statut": ["Ouvert"], "Telephone": ["03.62.53.79.41"], "Site": ["Faches Thumesnil "], "Mail": ["arousselot-doisy@immochan.com"], "Nb_boutiques": ["45"], "Contact": ["Angélique ROUSSELOT-DOISY"], "Surface_GLA": ["8000"], "Mobile": ["06.62.13.63.39"]}
{"Fonction": ["Responsable  commercialisation"], "Ville": ["ENGLOS "], "Surface_hyper": ["17160"], "Statut": ["Ouvert"], "Telephone": ["03.62.53.79.41"], "Site": ["Englos Les Géants "], "Mail": ["arousselot-doisy@immochan.com"], "Nb_boutiques": ["72"], "Contact": ["Angélique ROUSSELOT-DOISY"], "Surface_GLA": ["15000"], "Mobile": ["06.62.13.63.39"]}
{"Fonction": ["Responsable Galeries Marchandes"], "Ville": ["COLMENAR VIEJO - MADRID"], "Surface_hyper": ["8334"], "Statut": ["Ouvert"], "Telephone": [], "Site": ["EL VENTANAL DE LA SIERRA"], "Mail": [], "Nb_boutiques": ["71"], "Contact": [], "Surface_GLA": ["13165"], "Mobile": []}
{"Fonction": ["Responsable de commercialisation"], "Ville": ["BRASOV"], "Surface_hyper": ["6100"], "Statut": ["Ouvert"], "Telephone": [], "Site": ["Eliana Mall"], "Mail": ["ampop@immochan.com"], "Nb_boutiques": ["17"], "Contact": ["Anca Pop"], "Surface_GLA": ["765"], "Mobile": ["+ 40 748 05 12 74"]}
{"Fonction": ["Responsable Commercialisation"], "Ville": ["Fano"], "Surface_hyper": ["5040"], "Statut": ["Extension - Rénovation"], "Telephone": ["+39 02 57 58 48 64"], "Site": ["Fano"], "Mail": ["giampiero.dimaio@gcispa.com"], "Nb_boutiques": ["20"], "Contact": ["Giampiero DI MAIO"], "Surface_GLA": ["4592"], "Mobile": []}
{"Fonction": ["Responsable  commercialisation"], "Ville": ["DURY LES AMIENS"], "Surface_hyper": ["14000"], "Statut": ["Ouvert"], "Telephone": ["06.24.98.22.01"], "Site": ["Dury"], "Mail": ["cbarrois@immochan.com"], "Nb_boutiques": ["50"], "Contact": ["Christophe BARROIS"], "Surface_GLA": ["8300"], "Mobile": []}
{"Fonction": ["Responsable de commercialisation"], "Ville": ["Dunakeszi"], "Surface_hyper": ["20938"], "Statut": ["Extension - Rénovation"], "Telephone": ["+ 36 18 87 45 25"], "Site": ["Dunakeszi"], "Mail": ["h.cziegler@auchan.hu"], "Nb_boutiques": ["67"], "Contact": ["Helga CZIEGLER"], "Surface_GLA": ["9373"], "Mobile": ["+ 363 04 88 16 75"]}
{"Fonction": ["Responsable de commercialisation"], "Ville": ["BUCAREST"], "Surface_hyper": ["10500"], "Statut": ["Ouvert"], "Telephone": [], "Site": ["Drumul Taberei "], "Mail": ["oiancu@immochan.com"], "Nb_boutiques": ["119"], "Contact": ["Ofelia IANCU"], "Surface_GLA": ["9500"], "Mobile": []}
{"Fonction": ["Responsable  commercialisation"], "Ville": ["DOUAI"], "Surface_hyper": ["10800"], "Statut": ["Ouvert"], "Telephone": ["06.24.98.22.01"], "Site": ["Douai"], "Mail": ["cbarrois@immochan.com"], "Nb_boutiques": ["45"], "Contact": ["Christophe BARROIS"], "Surface_GLA": ["7500"], "Mobile": []}
{"Fonction": ["Responsable Galeries Marchandes"], "Ville": ["FERROL - LA CORUÑA"], "Surface_hyper": ["10045"], "Statut": ["Ouvert"], "Telephone": ["+ 34 91 730 66 66"], "Site": ["FERROL"], "Mail": ["angel.garcia@alcampo.es"], "Nb_boutiques": ["26"], "Contact": ["Angel GARCIA"], "Surface_GLA": ["2284"], "Mobile": ["+ 34 618 342 095"]}
{"Fonction": ["Responsable Galeries Marchandes"], "Ville": ["GRANADA"], "Surface_hyper": ["10988"], "Statut": ["Ouvert"], "Telephone": [], "Site": ["GRANADA"], "Mail": [], "Nb_boutiques": ["24"], "Contact": [], "Surface_GLA": ["3349"], "Mobile": []}
{"Fonction": ["Directrice Commerciale"], "Ville": ["Cracovie"], "Surface_hyper": ["16500"], "Statut": ["Ouvert"], "Telephone": [], "Site": ["Galeria Bronowice"], "Mail": [], "Nb_boutiques": ["160"], "Contact": [], "Surface_GLA": ["34840"], "Mobile": []}
{"Fonction": ["Responsable de commercialisation"], "Ville": ["Fót"], "Surface_hyper": ["13943"], "Statut": ["Ouvert"], "Telephone": ["+ 36 18 87 45 25"], "Site": ["Fót"], "Mail": ["h.cziegler@auchan.hu"], "Nb_boutiques": ["63"], "Contact": ["Helga CZIEGLER"], "Surface_GLA": ["5790"], "Mobile": ["+ 363 04 88 16 75"]}
{"Fonction": ["Responsable commercialisation"], "Ville": ["Giugliano in Campania"], "Surface_hyper": ["12085"], "Statut": ["Ouvert"], "Telephone": ["+ (02) 57 58 21 10"], "Site": ["Giugliano"], "Mail": ["ettore.papponetti@gcispa.com"], "Nb_boutiques": ["93"], "Contact": ["Ettore PAPPONETTI"], "Surface_GLA": ["58554"], "Mobile": ["+ 3 93 35 27 75 93"]}
{"Fonction": ["Responsable Galeries Marchandes"], "Ville": ["ROCES - GIJÓN"], "Surface_hyper": ["10524"], "Statut": ["Ouvert"], "Telephone": ["+ 34 91 730 66 66"], "Site": ["GIJÓN"], "Mail": ["angel.garcia@alcampo.es"], "Nb_boutiques": ["18"], "Contact": ["Angel GARCIA"], "Surface_GLA": ["1203"], "Mobile": ["+ 34 618 342 095"]}
{"Fonction": ["Directrice Commerciale"], "Ville": ["Gdańsk"], "Surface_hyper": ["12000"], "Statut": ["Extension - Rénovation"], "Telephone": ["+48 22 209 86 23"], "Site": ["Gdańsk"], "Mail": ["awalentek@immochan.com"], "Nb_boutiques": ["50"], "Contact": ["Ada Walentek"], "Surface_GLA": ["10000"], "Mobile": []}
{"Fonction": ["Responsable Galeries Marchandes"], "Ville": ["Fongshan"], "Surface_hyper": ["11646"], "Statut": ["Ouvert"], "Telephone": ["+ 88 82 27 95 28 88"], "Site": ["Fongshan"], "Mail": ["ga07@rt-mart.com.tw"], "Nb_boutiques": ["34"], "Contact": ["Roman LEE"], "Surface_GLA": ["2439"], "Mobile": []}
{"Fonction": ["Directeur de commercialisation"], "Ville": ["Rozzano Milan"], "Surface_hyper": ["11792"], "Statut": ["Ouvert"], "Telephone": ["+39 02 57 58 48 64"], "Site": ["Fiordaliso"], "Mail": ["giampiero.dimaio@gcispa.com"], "Nb_boutiques": ["123"], "Contact": ["Giampiero DI MAIO"], "Surface_GLA": ["31113"], "Mobile": []}
{"Fonction": ["Responsable commercialisation"], "Ville": ["PLAISIR"], "Surface_hyper": ["15000"], "Statut": ["Extension - Rénovation"], "Telephone": [], "Site": ["Grand Plaisir "], "Mail": ["sauneau@immochan.com"], "Nb_boutiques": ["65"], "Contact": ["Stéphanie Auneau"], "Surface_GLA": ["12800"], "Mobile": ["06.72.04.66.89"]}
{"Fonction": ["Responsable Galeries Marchandes"], "Ville": ["New Taipei"], "Surface_hyper": ["7174"], "Statut": ["Ouvert"], "Telephone": ["+ 88 82 27 95 28 88"], "Site": ["Jingping"], "Mail": ["ga06@rt-mart.com.tw"], "Nb_boutiques": ["7"], "Contact": ["Pat HO"], "Surface_GLA": ["152"], "Mobile": []}
{"Fonction": ["Directrice régionale des centres commerciaux"], "Ville": ["Jiaxing"], "Surface_hyper": ["10312"], "Statut": ["Extension - Rénovation"], "Telephone": ["+ (86) 021 25 05 21 32"], "Site": ["Jiaxing"], "Mail": ["hui.fan@auchan.com.cn"], "Nb_boutiques": ["61"], "Contact": ["Hui FAN"], "Surface_GLA": ["5145"], "Mobile": []}
{"Fonction": ["Responsable  commercialisation"], "Ville": ["HIRSON"], "Surface_hyper": ["750"], "Statut": ["Ouvert"], "Telephone": ["06.24.98.22.01"], "Site": ["Hirson"], "Mail": ["cbarrois@immochan.com"], "Nb_boutiques": ["4"], "Contact": ["Christophe BARROIS"], "Surface_GLA": ["4500"], "Mobile": []}
{"Fonction": [], "Ville": ["JEREZ - CADIZ"], "Surface_hyper": ["13259"], "Statut": ["Ouvert"], "Telephone": ["+ 34 91 730 66 66"], "Site": ["JEREZ"], "Mail": ["angel.garcia@alcampo.es"], "Nb_boutiques": ["16"], "Contact": ["Angel GARCIA"], "Surface_GLA": ["1786"], "Mobile": ["+ 34 618 342 095"]}
{"Fonction": ["Directrice régionale des centres commerciaux"], "Ville": ["Changxing"], "Surface_hyper": ["9736"], "Statut": ["Ouvert"], "Telephone": ["+ (86) 021 25 05 21 32"], "Site": ["Huzhou"], "Mail": ["hui.fan@auchan.com.cn"], "Nb_boutiques": ["52"], "Contact": ["Hui FAN"], "Surface_GLA": ["4410"], "Mobile": []}
{"Fonction": ["Directrice régionale des centres commerciaux"], "Ville": ["Hangzhou"], "Surface_hyper": ["9058"], "Statut": ["Ouvert"], "Telephone": ["+ (86) 021 25 05 21 32"], "Site": ["Hangzhou 1 Daguan"], "Mail": ["hui.fan@auchan.com.cn"], "Nb_boutiques": ["40"], "Contact": ["Hui FAN"], "Surface_GLA": ["3434"], "Mobile": []}
{"Fonction": ["Responsable des centres Canton"], "Ville": ["Guangzhou "], "Surface_hyper": ["9232"], "Statut": ["Ouvert"], "Telephone": ["+ (86) 020 38 08 32 50  "], "Site": ["Guangzhou Fafa Mall"], "Mail": ["jinquan.wang@auchan.com.cn"], "Nb_boutiques": ["15"], "Contact": ["Jingquan WANG"], "Surface_GLA": ["1077"], "Mobile": []}
{"Fonction": ["Responsable commercialisation"], "Ville": ["Grottammare"], "Surface_hyper": ["3614"], "Statut": ["Ouvert"], "Telephone": ["+ (02) 57 58 21 10"], "Site": ["Grottammare"], "Mail": ["ettore.papponetti@gcispa.com"], "Nb_boutiques": ["15"], "Contact": ["Ettore PAPPONETTI"], "Surface_GLA": ["4886"], "Mobile": ["+ 3 93 35 27 75 93"]}
{"Fonction": ["Responsable commercialisation"], "Ville": ["GRASSE CEDEX"], "Surface_hyper": ["1170"], "Statut": ["Ouvert"], "Telephone": ["04.13.60.06.06"], "Site": ["Grasse"], "Mail": ["clancelot@immochan.com"], "Nb_boutiques": ["13"], "Contact": ["Céline LANCELOT"], "Surface_GLA": ["7050"], "Mobile": ["06 28 96 41 51"]}
{"Fonction": ["Responsable région Sud"], "Ville": ["ALVERCA DO RIBATEJO"], "Surface_hyper": ["7700"], "Statut": ["Ouvert"], "Telephone": [], "Site": ["Jumbo de Alverca"], "Mail": [], "Nb_boutiques": ["15"], "Contact": [], "Surface_GLA": ["1071"], "Mobile": []}
{"Fonction": ["Responsable  commercialisation"], "Ville": ["EPINAY SUR SEINE"], "Surface_hyper": ["10000"], "Statut": ["Ouvert"], "Telephone": [], "Site": ["L'ilo "], "Mail": ["rmorel@immochan.com"], "Nb_boutiques": ["48"], "Contact": ["Romain MOREL"], "Surface_GLA": ["11000"], "Mobile": []}
{"Fonction": ["Responsable de commercialisation"], "Ville": ["Kecskemét"], "Surface_hyper": ["9340"], "Statut": ["Ouvert"], "Telephone": [], "Site": ["Kecskemét"], "Mail": [], "Nb_boutiques": ["40"], "Contact": [], "Surface_GLA": ["5781"], "Mobile": []}
{"Fonction": ["Responsable de commercialisation"], "Ville": ["Kiev"], "Surface_hyper": ["14300"], "Statut": ["Ouvert"], "Telephone": [], "Site": ["Kiev Petrivka"], "Mail": [], "Nb_boutiques": ["31"], "Contact": [], "Surface_GLA": ["2000"], "Mobile": []}
{"Fonction": ["Responsable de commercialisation"], "Ville": ["Kiev"], "Surface_hyper": ["16000"], "Statut": ["Ouvert"], "Telephone": [], "Site": ["Kiev Bielitchi "], "Mail": [], "Nb_boutiques": ["25"], "Contact": [], "Surface_GLA": ["1400"], "Mobile": []}
{"Fonction": [], "Ville": ["Kirchberg"], "Surface_hyper": [], "Statut": ["Ouvert"], "Telephone": [], "Site": ["Kirchberg"], "Mail": [], "Nb_boutiques": [], "Contact": [], "Surface_GLA": [], "Mobile": []}
{"Fonction": ["Responsable région Nord"], "Ville": ["VILA NOVA DE GAIA"], "Surface_hyper": ["3500"], "Statut": ["Ouvert"], "Telephone": [], "Site": ["Canidelo"], "Mail": [], "Nb_boutiques": ["9"], "Contact": [], "Surface_GLA": ["378"], "Mobile": []}
{"Fonction": ["Responsable région Sud"], "Ville": ["CASCAIS"], "Surface_hyper": ["5360"], "Statut": ["Ouvert"], "Telephone": [], "Site": ["Jumbo de Cascais"], "Mail": [], "Nb_boutiques": ["23"], "Contact": [], "Surface_GLA": ["1257"], "Mobile": []}
{"Fonction": ["Responsable région Nord"], "Ville": ["COUTO"], "Surface_hyper": ["4000"], "Statut": ["Ouvert"], "Telephone": [], "Site": ["St Tirso"], "Mail": [], "Nb_boutiques": ["13"], "Contact": [], "Surface_GLA": ["645"], "Mobile": []}
{"Fonction": ["Responsable région Nord"], "Ville": ["Vila Nova de Famalicão"], "Surface_hyper": ["4126"], "Statut": ["Ouvert"], "Telephone": [], "Site": ["Jumbo de Famalicão"], "Mail": [], "Nb_boutiques": ["34"], "Contact": [], "Surface_GLA": ["3223"], "Mobile": []}
{"Fonction": ["Responsable commercial"], "Ville": ["Luxembourg"], "Surface_hyper": ["12500"], "Statut": ["Nouveaux projets"], "Telephone": [], "Site": ["La Cloche d'Or - House of Brands"], "Mail": [""], "Nb_boutiques": ["120"], "Contact": ["Dimitri  COLLIGNON"], "Surface_GLA": ["75000"], "Mobile": []}
{"Fonction": ["Responsable commercialisation"], "Ville": ["Montivilliers "], "Surface_hyper": ["12500"], "Statut": ["Extension - Rénovation"], "Telephone": ["03.62.53.79.23"], "Site": ["Le Havre Montivilliers"], "Mail": ["fdarbois@immochan.com"], "Nb_boutiques": ["55"], "Contact": ["Frédéric DARBOIS"], "Surface_GLA": ["12500"], "Mobile": ["06.16.46.48.70"]}
{"Fonction": ["Responsable  commercialisation"], "Ville": ["LEERS"], "Surface_hyper": ["18178"], "Statut": ["Ouvert"], "Telephone": ["06.24.98.22.01"], "Site": ["Leers"], "Mail": ["cbarrois@immochan.com"], "Nb_boutiques": ["73"], "Contact": ["Christophe BARROIS"], "Surface_GLA": ["7300"], "Mobile": []}
{"Fonction": ["Responsable Galeries Marchandes"], "Ville": ["LA LAGUNA - TENERIFE"], "Surface_hyper": [], "Statut": ["Ouvert"], "Telephone": ["+ 34 91 730 66 66"], "Site": ["LA LAGUNA"], "Mail": ["jc.garcia@alcampo.es"], "Nb_boutiques": ["51"], "Contact": ["José Carlos GARCIA"], "Surface_GLA": ["9573"], "Mobile": ["+ 34 606 432 723"]}
{"Fonction": ["Responsable commercialisation"], "Ville": ["LA SEYNE SUR MER"], "Surface_hyper": ["11161"], "Statut": ["Ouvert"], "Telephone": ["04.13.60.06.06"], "Site": ["La Seyne-sur-Mer"], "Mail": ["clancelot@immochan.com"], "Nb_boutiques": ["45"], "Contact": ["Céline LANCELOT"], "Surface_GLA": ["6460"], "Mobile": ["06 28 96 41 51"]}
{"Fonction": ["Responsable  commercialisation"], "Ville": ["LE HAVRE"], "Surface_hyper": [], "Statut": ["Ouvert"], "Telephone": ["03.62.53.79.23"], "Site": ["Le Havre Mont Gaillard"], "Mail": ["fdarbois@immochan.com"], "Nb_boutiques": ["45"], "Contact": ["Frédéric DARBOIS"], "Surface_GLA": ["19000"], "Mobile": ["06.16.46.48.70"]}
{"Fonction": ["Responsable commercialisation"], "Ville": ["LA CHAPELLE ST AUBIN"], "Surface_hyper": ["13200"], "Statut": ["Ouvert"], "Telephone": ["05.24.57.96.42"], "Site": ["Le Mans "], "Mail": ["tnguyen@immochan.com"], "Nb_boutiques": ["71"], "Contact": ["Tuan NGUYEN"], "Surface_GLA": ["12000"], "Mobile": ["06.33.45.38.02"]}
{"Fonction": ["Responsable Galeries Marchandes"], "Ville": ["ALCALA DE HENARES"], "Surface_hyper": ["11412"], "Statut": ["Ouvert"], "Telephone": ["+ 34 91 730 66 66"], "Site": ["LA DEHESA"], "Mail": ["lf.ubeda@alcampo.es"], "Nb_boutiques": ["71"], "Contact": ["Luis UBEDA"], "Surface_GLA": ["10981"], "Mobile": ["+ 34 629 858 392"]}
{"Fonction": ["Responsable Galeries Marchandes"], "Ville": ["PAVALEA - LA CORUÑA"], "Surface_hyper": ["7868"], "Statut": ["Ouvert"], "Telephone": ["+ 34 91 730 66 66"], "Site": ["LA CORUÑA"], "Mail": ["angel.garcia@alcampo.es"], "Nb_boutiques": ["17"], "Contact": ["Angel GARCIA"], "Surface_GLA": ["823"], "Mobile": ["+ 34 618 342 095"]}
{"Fonction": ["Responsable commercialisation "], "Ville": ["MEAUX"], "Surface_hyper": ["12000"], "Statut": ["Ouvert"], "Telephone": [], "Site": ["Les Saisons de Meaux "], "Mail": ["atesquet@immochan.com"], "Nb_boutiques": ["100"], "Contact": ["Alexandre TESQUET"], "Surface_GLA": ["30000"], "Mobile": []}
{"Fonction": ["Responsable commerciale "], "Ville": ["Maurepas "], "Surface_hyper": ["11175"], "Statut": ["Ouvert"], "Telephone": [], "Site": ["Maurepas - Pariwest "], "Mail": ["sauneau@immochan.com"], "Nb_boutiques": ["32"], "Contact": ["Stéphanie Auneau"], "Surface_GLA": ["3300"], "Mobile": ["06.72.04.66.89"]}
{"Fonction": ["Responsable commercialisation"], "Ville": ["Martigues"], "Surface_hyper": ["14029"], "Statut": ["Ouvert"], "Telephone": [], "Site": ["MARTIGUES"], "Mail": ["sleon@immochan.com"], "Nb_boutiques": ["54"], "Contact": ["Sandrine LEON"], "Surface_GLA": ["9417"], "Mobile": []}
{"Fonction": ["Responsable Commercialisation"], "Ville": ["Mantes"], "Surface_hyper": ["12210"], "Statut": ["Ouvert"], "Telephone": [], "Site": ["Mantes - Buchelay"], "Mail": ["sauneau@immochan.com"], "Nb_boutiques": ["30"], "Contact": ["Stéphanie Auneau"], "Surface_GLA": ["5700"], "Mobile": ["06.72.04.66.89"]}
{"Fonction": ["Responsable de commercialisation"], "Ville": ["Maglód"], "Surface_hyper": ["12156"], "Statut": ["Ouvert"], "Telephone": [], "Site": ["Maglód"], "Mail": [], "Nb_boutiques": ["51"], "Contact": [], "Surface_GLA": ["6290"], "Mobile": []}
{"Fonction": ["Responsable  commercialisation"], "Ville": ["DARDILLY "], "Surface_hyper": ["9500"], "Statut": ["Extension - Rénovation"], "Telephone": ["04.13.60.06.06"], "Site": ["Lyon Dardilly"], "Mail": ["clancelot@immochan.com"], "Nb_boutiques": ["35"], "Contact": ["Céline LANCELOT"], "Surface_GLA": ["3143"], "Mobile": ["06 28 96 41 51"]}
{"Fonction": ["Responsable  commercialisation"], "Ville": ["ST PRIEST"], "Surface_hyper": [], "Statut": ["Ouvert"], "Telephone": ["04 13 60 06 07"], "Site": ["Lyon Porte des Alpes "], "Mail": ["dbenisty@immochan.com"], "Nb_boutiques": [], "Contact": ["Delphine BENISTY"], "Surface_GLA": ["11600"], "Mobile": ["06 03 23 39 64"]}
{"Fonction": ["Responsable commercialisation"], "Ville": ["CALUIRE"], "Surface_hyper": ["10800"], "Statut": ["Ouvert"], "Telephone": ["04.13.60.06.06"], "Site": ["Lyon Caluire"], "Mail": ["clancelot@immochan.com"], "Nb_boutiques": ["43"], "Contact": ["Céline LANCELOT"], "Surface_GLA": ["6500"], "Mobile": ["06 28 96 41 51"]}
{"Fonction": ["Responsable Galeries Marchandes"], "Ville": ["LINARES - JAÉN"], "Surface_hyper": ["6090"], "Statut": ["Ouvert"], "Telephone": ["+ 34 91 730 66 66"], "Site": ["LINARES"], "Mail": ["angel.garcia@alcampo.es"], "Nb_boutiques": ["21"], "Contact": ["Angel GARCIA"], "Surface_GLA": ["1556"], "Mobile": ["+ 34 618 342 095"]}
{"Fonction": ["Responsable  commercialisation"], "Ville": ["LOUVROIL"], "Surface_hyper": ["15300"], "Statut": ["Extension - Rénovation"], "Telephone": ["06.24.98.22.01"], "Site": ["Louvroil"], "Mail": ["cbarrois@immochan.com"], "Nb_boutiques": ["70"], "Contact": ["Christophe BARROIS"], "Surface_GLA": ["10700"], "Mobile": []}
{"Fonction": ["Directeur de commercialisation"], "Ville": ["Mazzano Brescia"], "Surface_hyper": ["9584"], "Statut": ["Ouvert"], "Telephone": ["+39 02 57 58 48 64"], "Site": ["Mazzano"], "Mail": ["giampiero.dimaio@gcispa.com"], "Nb_boutiques": ["46"], "Contact": ["Giampiero DI MAIO"], "Surface_GLA": ["12117"], "Mobile": []}
{"Fonction": ["Responsable  commercialisation"], "Ville": ["DOMERAT"], "Surface_hyper": ["6515"], "Statut": ["Ouvert"], "Telephone": [], "Site": ["Montluçon Domerat"], "Mail": [""], "Nb_boutiques": ["27"], "Contact": ["Hélène RIBIERRE"], "Surface_GLA": ["3162"], "Mobile": []}
{"Fonction": ["Responsable commercialisation"], "Ville": ["SEMECOURT"], "Surface_hyper": ["15547"], "Statut": ["Ouvert"], "Telephone": ["01.77.51.00.69"], "Site": ["Metz Semécourt "], "Mail": ["ngauthier@immochan.com"], "Nb_boutiques": ["77"], "Contact": ["Nathalie GAUTHIER"], "Surface_GLA": ["28654"], "Mobile": ["06.23.34.44.40"]}
{"Fonction": ["Chargée de commercialisation"], "Ville": ["MONTAUBAN"], "Surface_hyper": ["6500"], "Statut": ["Ouvert"], "Telephone": ["05 24 57 96 15"], "Site": ["Montauban "], "Mail": ["cparasie@immochan.com"], "Nb_boutiques": ["33"], "Contact": ["Charlotte PARASIE"], "Surface_GLA": ["5000"], "Mobile": ["06.21.35.45.91"]}
{"Fonction": ["Responsable de commercialisation"], "Ville": ["Miskolc"], "Surface_hyper": ["10903"], "Statut": ["Ouvert"], "Telephone": ["+ 36 18 87 45 25"], "Site": ["Miskolc II"], "Mail": ["h.cziegler@auchan.hu"], "Nb_boutiques": ["29"], "Contact": ["Helga CZIEGLER"], "Surface_GLA": ["3110"], "Mobile": ["+ 363 04 88 16 75"]}
{"Fonction": ["Responsable de commercialisation"], "Ville": ["Miskolc"], "Surface_hyper": ["12236"], "Statut": ["Ouvert"], "Telephone": ["+ 36 18 87 45 25"], "Site": ["Miskolc"], "Mail": ["h.cziegler@auchan.hu"], "Nb_boutiques": ["50"], "Contact": ["Helga CZIEGLER"], "Surface_GLA": ["6193"], "Mobile": ["+ 363 04 88 16 75"]}
{"Fonction": ["Directeur de commercialisation"], "Ville": ["Mestre"], "Surface_hyper": ["10598"], "Statut": ["Ouvert"], "Telephone": ["+39 02 57 58 48 64"], "Site": ["Mestre"], "Mail": ["giampiero.dimaio@gcispa.com"], "Nb_boutiques": ["123"], "Contact": ["Giampiero DI MAIO"], "Surface_GLA": ["28954"], "Mobile": []}
{"Fonction": ["Responsable  commercialisation"], "Ville": ["MERS LES BAINS"], "Surface_hyper": ["7000"], "Statut": ["Ouvert"], "Telephone": ["03.62.53.79.41"], "Site": ["Mers Les Bains "], "Mail": ["arousselot-doisy@immochan.com"], "Nb_boutiques": ["12"], "Contact": ["Angélique ROUSSELOT-DOISY"], "Surface_GLA": ["1700"], "Mobile": ["06.62.13.63.39"]}
{"Fonction": ["Directeur de commercialisation"], "Ville": ["Merate Lecco"], "Surface_hyper": ["6773"], "Statut": ["Ouvert"], "Telephone": ["+39 02 57 58 48 64"], "Site": ["Merate"], "Mail": ["giampiero.dimaio@gcispa.com"], "Nb_boutiques": ["30"], "Contact": ["Giampiero DI MAIO"], "Surface_GLA": ["8228"], "Mobile": []}
{"Fonction": ["Responsable des centres Canton"], "Ville": ["Xingning"], "Surface_hyper": [], "Statut": ["Ouvert"], "Telephone": ["+ (86) 020 38 08 32 50  "], "Site": ["Meizhou - Xingning"], "Mail": ["jinquan.wang@auchan.com.cn"], "Nb_boutiques": ["37"], "Contact": ["Jingquan WANG"], "Surface_GLA": ["3934"], "Mobile": []}
{"Fonction": ["Directeur de commercialisation"], "Ville": ["Monza"], "Surface_hyper": ["7767"], "Statut": ["Ouvert"], "Telephone": ["+39 02 57 58 48 64"], "Site": ["Monza"], "Mail": ["giampiero.dimaio@gcispa.com"], "Nb_boutiques": ["70"], "Contact": ["Giampiero DI MAIO"], "Surface_GLA": ["14193"], "Mobile": []}
{"Fonction": ["Directrice régionale des centres commerciaux"], "Ville": ["Nanjing"], "Surface_hyper": ["10363"], "Statut": ["Ouvert"], "Telephone": ["+ (86) 021 25 05 21 32"], "Site": ["Nanjing 1 Hanzhongmen"], "Mail": ["hui.fan@auchan.com.cn"], "Nb_boutiques": ["31"], "Contact": ["Hui FAN"], "Surface_GLA": ["1597"], "Mobile": []}
{"Fonction": ["Responsable commercialisation"], "Ville": ["LAXOU"], "Surface_hyper": ["10905"], "Statut": ["Ouvert"], "Telephone": ["01.77.51.00.69"], "Site": ["Nancy Laxou "], "Mail": ["ngauthier@immochan.com"], "Nb_boutiques": ["36"], "Contact": ["Nathalie GAUTHIER"], "Surface_GLA": ["5146"], "Mobile": ["06.23.34.44.40"]}
{"Fonction": ["Directrice régionale des centres commerciaux"], "Ville": ["Nanjing"], "Surface_hyper": ["9050"], "Statut": ["Ouvert"], "Telephone": ["+ (86) 021 25 05 21 32"], "Site": ["Nanjing 3 Yingtian"], "Mail": ["hui.fan@auchan.com.cn"], "Nb_boutiques": ["49"], "Contact": ["Hui FAN"], "Surface_GLA": ["6417"], "Mobile": []}
{"Fonction": ["Directrice régionale des centres commerciaux"], "Ville": ["Nanjing"], "Surface_hyper": ["10356"], "Statut": ["Ouvert"], "Telephone": ["+ (86) 021 25 05 21 32"], "Site": ["Nanjing 2 Jiangning"], "Mail": ["hui.fan@auchan.com.cn"], "Nb_boutiques": ["79"], "Contact": ["Hui FAN"], "Surface_GLA": ["11065"], "Mobile": []}
{"Fonction": ["Directrice régionale des centres commerciaux"], "Ville": ["Nanchang"], "Surface_hyper": ["12020"], "Statut": ["Ouvert"], "Telephone": ["+ (86) 021 25 05 21 32"], "Site": ["Nanchang"], "Mail": ["hui.fan@auchan.com.cn"], "Nb_boutiques": ["63"], "Contact": ["Hui FAN"], "Surface_GLA": ["9524"], "Mobile": []}
{"Fonction": ["Responsable commercialisation"], "Ville": ["NANCY"], "Surface_hyper": ["1355"], "Statut": ["Ouvert"], "Telephone": ["01.77.51.00.69"], "Site": ["Nancy Lobau "], "Mail": ["ngauthier@immochan.com"], "Nb_boutiques": ["12"], "Contact": ["Nathalie GAUTHIER"], "Surface_GLA": ["6450"], "Mobile": ["06.23.34.44.40"]}
{"Fonction": ["Responsable commercialisation"], "Ville": ["Mugnano Di Napoli"], "Surface_hyper": ["9100"], "Statut": ["Ouvert"], "Telephone": ["+ (02) 57 58 21 10"], "Site": ["Mugnano"], "Mail": ["ettore.papponetti@gcispa.com"], "Nb_boutiques": ["42"], "Contact": ["Ettore PAPPONETTI"], "Surface_GLA": ["9445"], "Mobile": ["+ 3 93 35 27 75 93"]}
{"Fonction": ["Responsable Galeries Marchandes"], "Ville": ["MOTRIL - GRANADA"], "Surface_hyper": ["7351"], "Statut": ["Ouvert"], "Telephone": [], "Site": ["MOTRIL"], "Mail": [], "Nb_boutiques": ["13"], "Contact": [], "Surface_GLA": ["572"], "Mobile": []}
{"Fonction": ["Responsable Galeries Marchandes"], "Ville": ["MADRID"], "Surface_hyper": ["11400"], "Statut": ["Ouvert"], "Telephone": ["+ 34 91 730 66 66"], "Site": ["MORATALAZ"], "Mail": ["angel.garcia@alcampo.es"], "Nb_boutiques": ["24"], "Contact": ["Angel GARCIA"], "Surface_GLA": ["1694"], "Mobile": ["+ 34 618 342 095"]}
{"Fonction": ["Responsable  commercialisation"], "Ville": ["ST SEBASTIEN SUR LOIRE"], "Surface_hyper": ["10100"], "Statut": ["Ouvert"], "Telephone": ["05.24.57.96.42"], "Site": ["Nantes Saint Sébastien "], "Mail": ["tnguyen@immochan.com"], "Nb_boutiques": ["76"], "Contact": ["Tuan NGUYEN"], "Surface_GLA": ["10900"], "Mobile": ["06.33.45.38.02"]}
{"Fonction": ["Directrice régionale des centrès commerciaux"], "Ville": ["Ningbo"], "Surface_hyper": [], "Statut": ["Ouvert"], "Telephone": ["+ (86) 021 25 05 21 32"], "Site": ["Ningbo Jiangshan"], "Mail": ["hui.fan@auchan.com.cn"], "Nb_boutiques": [], "Contact": ["Hui FAN"], "Surface_GLA": ["2050"], "Mobile": []}
{"Fonction": ["Directrice régionale des centres commerciaux"], "Ville": ["Ningbo"], "Surface_hyper": ["10910"], "Statut": ["Ouvert"], "Telephone": ["+ (86) 021 25 05 21 32"], "Site": ["Ningbo 2 Jiangdong"], "Mail": ["hui.fan@auchan.com.cn"], "Nb_boutiques": ["45"], "Contact": ["Hui FAN"], "Surface_GLA": ["3078"], "Mobile": []}
{"Fonction": ["Responsable Galeries Marchandes"], "Ville": ["Taipei"], "Surface_hyper": ["10801"], "Statut": ["Ouvert"], "Telephone": ["+ 88 82 27 95 28 88"], "Site": ["Neihu 2"], "Mail": ["ga06@rt-mart.com.tw"], "Nb_boutiques": ["58"], "Contact": ["Pat HO"], "Surface_GLA": ["5082"], "Mobile": []}
{"Fonction": ["Directrice régionale des centres commerciaux"], "Ville": ["Ningbo"], "Surface_hyper": ["9120"], "Statut": ["Ouvert"], "Telephone": ["+ (86) 021 25 05 21 32"], "Site": ["Ningbo 1 Haishu"], "Mail": ["hui.fan@auchan.com.cn"], "Nb_boutiques": ["54"], "Contact": ["Hui FAN"], "Surface_GLA": ["3300"], "Mobile": []}
{"Fonction": ["Directeur de commercialisation"], "Ville": ["Nerviano Milan"], "Surface_hyper": ["7789"], "Statut": ["Ouvert"], "Telephone": ["+39 02 57 58 48 64"], "Site": ["Nerviano"], "Mail": ["giampiero.dimaio@gcispa.com"], "Nb_boutiques": ["22"], "Contact": ["Giampiero DI MAIO"], "Surface_GLA": ["2581"], "Mobile": []}
{"Fonction": ["Responsable commercialisation"], "Ville": ["NOGENT SUR OISE"], "Surface_hyper": ["12500"], "Statut": ["Ouvert"], "Telephone": [], "Site": ["Nogent-sur-Oise"], "Mail": ["sauneau@immochan.com"], "Nb_boutiques": ["40"], "Contact": ["Stéphanie Auneau"], "Surface_GLA": ["7600"], "Mobile": ["06.72.04.66.89"]}
{"Fonction": ["Responsable Galeries Marchandes"], "Ville": ["Taipei"], "Surface_hyper": ["10045"], "Statut": ["Ouvert"], "Telephone": ["+ 88 82 27 95 28 88"], "Site": ["Neihu 1"], "Mail": ["ga06@rt-mart.com.tw"], "Nb_boutiques": ["40"], "Contact": ["Pat HO"], "Surface_GLA": ["2624"], "Mobile": []}
{"Fonction": ["Responsable commercialisation"], "Ville": ["Naples"], "Surface_hyper": ["8830"], "Statut": ["Ouvert"], "Telephone": ["+ (02) 57 58 21 10"], "Site": ["Napoli Argine"], "Mail": ["ettore.papponetti@gcispa.com"], "Nb_boutiques": ["83"], "Contact": ["Ettore PAPPONETTI"], "Surface_GLA": ["14043"], "Mobile": ["+ 3 93 35 27 75 93"]}
{"Fonction": ["Responsable Galeries Marchandes"], "Ville": ["Hsin Chu 300"], "Surface_hyper": ["10203"], "Statut": ["Ouvert"], "Telephone": ["+ 88 82 27 95 28 88"], "Site": ["Nanya"], "Mail": ["ga08@rt-mart.com.tw"], "Nb_boutiques": ["29"], "Contact": ["Rick HSU"], "Surface_GLA": ["1936"], "Mobile": []}
{"Fonction": ["Responsable commerciale"], "Ville": ["Noyelles Godault"], "Surface_hyper": ["21850"], "Statut": ["Extension - Rénovation"], "Telephone": ["03.62.53.79.05"], "Site": ["Noyelles Godault "], "Mail": ["tgouy@immochan.com"], "Nb_boutiques": ["78"], "Contact": ["Thérèse GOUY"], "Surface_GLA": ["14700"], "Mobile": ["06.28.90.22.62"]}
{"Fonction": ["Responsable Galeries Marchandes"], "Ville": ["MARRATXI - PALMA DE MALLORCA"], "Surface_hyper": ["12162"], "Statut": ["Ouvert"], "Telephone": ["+ 34 91 730 66 66"], "Site": ["PALMA DE MALLORCA"], "Mail": ["p.gomez-peralta@alcampo.es"], "Nb_boutiques": ["45"], "Contact": ["Pablo GOMEZ"], "Surface_GLA": ["6394"], "Mobile": ["+ 34 669 502 976"]}
{"Fonction": ["Responsable Galeries Marchandes"], "Ville": ["LOGROÑO"], "Surface_hyper": ["11433"], "Statut": ["Ouvert"], "Telephone": [], "Site": ["PARQUE RIOJA"], "Mail": [], "Nb_boutiques": ["71"], "Contact": [], "Surface_GLA": ["16766"], "Mobile": []}
{"Fonction": ["Responsable commercialisation"], "Ville": ["OSNY"], "Surface_hyper": ["9160"], "Statut": ["Ouvert"], "Telephone": [], "Site": ["Osny"], "Mail": [""], "Nb_boutiques": ["34"], "Contact": ["Marie-Christine BOUVET"], "Surface_GLA": ["20700"], "Mobile": []}
{"Fonction": [], "Ville": ["PAU"], "Surface_hyper": ["9600"], "Statut": ["Ouvert"], "Telephone": ["05 24 57 96 15"], "Site": ["Pau"], "Mail": ["cparasie@immochan.com"], "Nb_boutiques": ["26"], "Contact": ["Charlotte PARASIE"], "Surface_GLA": ["3400"], "Mobile": ["06.21.35.45.91"]}
{"Fonction": ["Directeur de commercialisation"], "Ville": ["Padova"], "Surface_hyper": ["6812"], "Statut": ["Ouvert"], "Telephone": ["+39 02 57 58 48 64"], "Site": ["Padova"], "Mail": ["giampiero.dimaio@gcispa.com"], "Nb_boutiques": ["23"], "Contact": ["Giampiero DI MAIO"], "Surface_GLA": ["3340"], "Mobile": []}
{"Fonction": [], "Ville": ["ORLEANS"], "Surface_hyper": [], "Statut": ["Ouvert"], "Telephone": [], "Site": ["Orléans Saint Jean de la Ruelle"], "Mail": [], "Nb_boutiques": ["62"], "Contact": [], "Surface_GLA": ["10000"], "Mobile": []}
{"Fonction": ["Responsable  commercialisation"], "Ville": ["OLIVET"], "Surface_hyper": ["10655"], "Statut": ["Ouvert"], "Telephone": [], "Site": ["Orléans Olivet "], "Mail": [], "Nb_boutiques": ["15"], "Contact": [], "Surface_GLA": ["2727"], "Mobile": []}
{"Fonction": ["Responsable commercialisation"], "Ville": ["Olbia"], "Surface_hyper": ["7000"], "Statut": ["Ouvert"], "Telephone": ["+ (02) 57 58 21 10"], "Site": ["Olbia"], "Mail": ["ettore.papponetti@gcispa.com"], "Nb_boutiques": ["57"], "Contact": ["Ettore PAPPONETTI"], "Surface_GLA": ["11881"], "Mobile": ["+ 3 93 35 27 75 93"]}
{"Fonction": ["Responsable de commercialisation"], "Ville": ["Budapest"], "Surface_hyper": ["11225"], "Statut": ["Ouvert"], "Telephone": ["+ 36 18 87 45 42"], "Site": ["Óbuda"], "Mail": ["t.zacharilles@auchan.hu"], "Nb_boutiques": ["19"], "Contact": ["Tamás ZACHAR ILLÉS"], "Surface_GLA": ["692"], "Mobile": ["+ 363 02 74 56 49"]}
{"Fonction": ["Responsable commercialisation"], "Ville": ["PERIGUEUX "], "Surface_hyper": ["10000"], "Statut": ["Extension - Rénovation"], "Telephone": ["05 24 57 96 15"], "Site": ["Périgueux- Marsac"], "Mail": ["cparasie@immochan.com"], "Nb_boutiques": ["30"], "Contact": ["Charlotte PARASIE"], "Surface_GLA": ["3920"], "Mobile": ["06.21.35.45.91"]}
{"Fonction": ["Responsable commercialisation"], "Ville": ["MONT SAINT MARTIN"], "Surface_hyper": ["13215"], "Statut": ["Extension - Rénovation"], "Telephone": ["01 47 62 61 68"], "Site": ["Pôle Europe Mont Saint Martin "], "Mail": ["fmoreau@immochan.com"], "Nb_boutiques": ["55"], "Contact": ["Frédérike  MOREAU"], "Surface_GLA": ["8600"], "Mobile": ["06 29 75 75 17"]}
{"Fonction": ["Responsable commercialisation"], "Ville": ["Catania"], "Surface_hyper": ["12713"], "Statut": ["Ouvert"], "Telephone": ["+ (02) 57 58 21 10"], "Site": ["Porte Di Catania"], "Mail": ["ettore.papponetti@gcispa.com"], "Nb_boutiques": ["146"], "Contact": ["Ettore PAPPONETTI"], "Surface_GLA": ["52704"], "Mobile": ["+ 3 93 35 27 75 93"]}
{"Fonction": ["Responsable Galeries Marchandes"], "Ville": ["MADRID"], "Surface_hyper": ["6434"], "Statut": ["Ouvert"], "Telephone": ["+ 34 91 730 66 66"], "Site": ["PIO XII"], "Mail": ["p.gomez-peralta@alcampo.es"], "Nb_boutiques": ["24"], "Contact": ["Pablo GOMEZ"], "Surface_GLA": ["1359"], "Mobile": ["+ 34 669 502 976"]}
{"Fonction": ["Responsable commercialisation"], "Ville": ["Pompei"], "Surface_hyper": ["6904"], "Statut": ["Ouvert"], "Telephone": ["+ (02) 57 58 21 10"], "Site": ["Pompei"], "Mail": ["ettore.papponetti@gcispa.com"], "Nb_boutiques": ["21"], "Contact": ["Ettore PAPPONETTI"], "Surface_GLA": ["1600"], "Mobile": ["+ 3 93 35 27 75 93"]}
{"Fonction": ["Responsable de commercialisation"], "Ville": ["PITESTI"], "Surface_hyper": ["12500"], "Statut": ["Ouvert"], "Telephone": [], "Site": ["Pitesti "], "Mail": ["oiancu@immochan.com"], "Nb_boutiques": ["37"], "Contact": ["Ofelia IANCU"], "Surface_GLA": ["4740"], "Mobile": []}
{"Fonction": ["Responsable Galeries Marchandes"], "Ville": ["Comté de Taoyuan, Canton de Fuxing"], "Surface_hyper": ["10464"], "Statut": ["Ouvert"], "Telephone": ["+ 88 82 27 95 28 88"], "Site": ["Pingchen"], "Mail": ["ga08@rt-mart.com.tw"], "Nb_boutiques": ["16"], "Contact": ["Rick HSU"], "Surface_GLA": ["598"], "Mobile": []}
{"Fonction": ["Responsable commercialisation"], "Ville": ["PETITE FORET"], "Surface_hyper": ["15400"], "Statut": ["Ouvert"], "Telephone": ["03.62.53.79.23"], "Site": ["Petite Forêt "], "Mail": ["fdarbois@immochan.com"], "Nb_boutiques": ["45"], "Contact": ["Frédéric DARBOIS"], "Surface_GLA": ["7600"], "Mobile": ["06.16.46.48.70"]}
{"Fonction": ["Responsable commercialisation"], "Ville": ["Pescara"], "Surface_hyper": ["8902"], "Statut": ["Ouvert"], "Telephone": ["+ (02) 57 58 21 10"], "Site": ["Pescara"], "Mail": ["ettore.papponetti@gcispa.com"], "Nb_boutiques": ["35"], "Contact": ["Ettore PAPPONETTI"], "Surface_GLA": ["6056"], "Mobile": ["+ 3 93 35 27 75 93"]}
{"Fonction": ["Responsable commercialisation"], "Ville": ["PERPIGNAN "], "Surface_hyper": ["11600"], "Statut": ["Ouvert"], "Telephone": [], "Site": ["Perpignan"], "Mail": ["amiel@immochan.com"], "Nb_boutiques": ["55"], "Contact": ["Aurore MIEL"], "Surface_GLA": ["14000"], "Mobile": ["06.46.15.75.09"]}
{"Fonction": ["Responsable commercialisation"], "Ville": ["Porto Sant'Elpidio"], "Surface_hyper": ["4458"], "Statut": ["Ouvert"], "Telephone": ["+ (02) 57 58 21 10"], "Site": ["Porto Sant'Elpidio"], "Mail": ["ettore.papponetti@gcispa.com"], "Nb_boutiques": ["39"], "Contact": ["Ettore PAPPONETTI"], "Surface_GLA": ["10599"], "Mobile": ["+ 3 93 35 27 75 93"]}
{"Fonction": ["Responsable Galeries Marchandes"], "Ville": ["SANT QUIRZE - BARCELONA"], "Surface_hyper": ["12524"], "Statut": ["Ouvert"], "Telephone": ["+ 34 91 730 66 66"], "Site": ["SANT QUIRZE"], "Mail": ["lf.ubeda@alcampo.es"], "Nb_boutiques": ["20"], "Contact": ["Luis UBEDA"], "Surface_GLA": ["1883"], "Mobile": ["+ 34 629 858 392"]}
{"Fonction": ["Responsable Galeries Marchandes"], "Ville": ["SANT BOI - BARCELONA"], "Surface_hyper": ["13942"], "Statut": ["Ouvert"], "Telephone": ["+ 34 91 730 66 66"], "Site": ["SANT BOI"], "Mail": ["lf.ubeda@alcampo.es"], "Nb_boutiques": ["61"], "Contact": ["Luis UBEDA"], "Surface_GLA": ["5331"], "Mobile": ["+ 34 629 858 392"]}
{"Fonction": ["Responsable commercialisation"], "Ville": ["LONGUENESSE"], "Surface_hyper": ["11000"], "Statut": ["Ouvert"], "Telephone": ["03.62.53.79.41"], "Site": ["Saint Omer Longuenesse "], "Mail": ["arousselot-doisy@immochan.com"], "Nb_boutiques": ["60"], "Contact": ["Angélique ROUSSELOT-DOISY"], "Surface_GLA": ["8000"], "Mobile": ["06.62.13.63.39"]}
{"Fonction": ["Responsable Galeries Marchandes"], "Ville": ["BARCELONA"], "Surface_hyper": ["12208"], "Statut": ["Ouvert"], "Telephone": ["+ 34 91 730 66 66"], "Site": ["SANT ADRIÁ"], "Mail": ["lf.ubeda@alcampo.es"], "Nb_boutiques": ["42"], "Contact": ["Luis UBEDA"], "Surface_GLA": ["6448"], "Mobile": ["+ 34 629 858 392"]}
{"Fonction": ["Responsable  commercialisation"], "Ville": ["ST QUENTIN"], "Surface_hyper": ["10000"], "Statut": ["Ouvert"], "Telephone": ["03.62.53.79.41"], "Site": ["Saint Quentin "], "Mail": ["arousselot-doisy@immochan.com"], "Nb_boutiques": ["60"], "Contact": ["Angélique ROUSSELOT-DOISY"], "Surface_GLA": ["9000"], "Mobile": ["06.62.13.63.39"]}
{"Fonction": ["Directeur de commercialisation"], "Ville": ["San Rocco al Porto Lodi"], "Surface_hyper": ["9707"], "Statut": ["Ouvert"], "Telephone": ["+39 02 57 58 48 64"], "Site": ["San Rocco al Porto"], "Mail": ["giampiero.dimaio@gcispa.com"], "Nb_boutiques": ["38"], "Contact": ["Giampiero DI MAIO"], "Surface_GLA": ["6941"], "Mobile": []}
{"Fonction": ["Responsable  commercialisation"], "Ville": ["RONCQ"], "Surface_hyper": ["15200"], "Statut": ["Ouvert"], "Telephone": ["03.62.53.79.05"], "Site": ["Roncq "], "Mail": ["tgouy@immochan.com"], "Nb_boutiques": ["40"], "Contact": ["Thérèse GOUY"], "Surface_GLA": ["25946"], "Mobile": ["06.28.90.22.62"]}
{"Fonction": ["Directeur de commercialisation"], "Ville": ["Turin"], "Surface_hyper": ["5740"], "Statut": ["Ouvert"], "Telephone": ["+39 02 57 58 48 64"], "Site": ["Rivoli"], "Mail": ["giampiero.dimaio@gcispa.com"], "Nb_boutiques": ["18"], "Contact": ["Giampiero DI MAIO"], "Surface_GLA": ["1445"], "Mobile": []}
{"Fonction": ["Responsable Commercialisation"], "Ville": ["Rescaldina Milan"], "Surface_hyper": ["15339"], "Statut": ["Extension - Rénovation"], "Telephone": ["+39 02 57 58 48 64"], "Site": ["Rescaldina"], "Mail": ["giampiero.dimaio@gcispa.com"], "Nb_boutiques": ["73"], "Contact": ["Giampiero DI MAIO"], "Surface_GLA": ["19525"], "Mobile": []}
{"Fonction": ["Responsable commercialisation"], "Ville": ["Predda Niedda"], "Surface_hyper": ["7358"], "Statut": ["Ouvert"], "Telephone": ["+ (02) 57 58 21 10"], "Site": ["Sassari Predda Niedda"], "Mail": ["ettore.papponetti@gcispa.com"], "Nb_boutiques": ["49"], "Contact": ["Ettore PAPPONETTI"], "Surface_GLA": ["14421"], "Mobile": ["+ 3 93 35 27 75 93"]}
{"Fonction": ["Directrice régionale des centres commerciaux"], "Ville": ["Shanghai"], "Surface_hyper": [], "Statut": ["Ouvert"], "Telephone": ["+ (86) 021 25 05 21 32"], "Site": ["Shanghai - Zhangjiang"], "Mail": ["hui.fan@auchan.com.cn"], "Nb_boutiques": ["22"], "Contact": ["Hui FAN"], "Surface_GLA": ["3912"], "Mobile": []}
{"Fonction": ["Responsable Galeries Marchandes"], "Ville": ["SEVILLA"], "Surface_hyper": ["10681"], "Statut": ["Ouvert"], "Telephone": ["+ 34 91 730 66 66"], "Site": ["SEVILLA"], "Mail": ["jc.garcia@alcampo.es"], "Nb_boutiques": ["39"], "Contact": ["José Carlos GARCIA"], "Surface_GLA": ["10994"], "Mobile": ["+ 34 606 432 723"]}
{"Fonction": ["Directrice régionale des centres commerciaux"], "Ville": ["Shanghai"], "Surface_hyper": ["424"], "Statut": ["Ouvert"], "Telephone": ["+ (86) 021 25 05 21 32"], "Site": ["Shanghai Changyang YP1 "], "Mail": ["hui.fan@auchan.com.cn"], "Nb_boutiques": ["41"], "Contact": ["Hui FAN"], "Surface_GLA": ["6915"], "Mobile": []}
{"Fonction": ["Directrice régionale des centres commerciaux"], "Ville": ["Shanghai"], "Surface_hyper": [], "Statut": ["Ouvert"], "Telephone": ["+ (86) 021 25 05 21 32"], "Site": ["Shanghai - Waigaoqiao"], "Mail": ["hui.fan@auchan.com.cn"], "Nb_boutiques": ["38"], "Contact": ["Hui FAN"], "Surface_GLA": ["3100"], "Mobile": []}
{"Fonction": ["Responsable  commercialisation"], "Ville": ["SETE"], "Surface_hyper": ["5300"], "Statut": ["Ouvert"], "Telephone": [], "Site": ["Sète"], "Mail": ["amiel@immochan.com"], "Nb_boutiques": ["21"], "Contact": ["Aurore MIEL"], "Surface_GLA": ["1142"], "Mobile": ["06.46.15.75.09"]}
{"Fonction": ["Responsable commercialisation"], "Ville": ["Senigallia Ancône"], "Surface_hyper": ["3853"], "Statut": ["Ouvert"], "Telephone": ["+ (02) 57 58 21 10"], "Site": ["Senigallia"], "Mail": ["ettore.papponetti@gcispa.com"], "Nb_boutiques": ["22"], "Contact": ["Ettore PAPPONETTI"], "Surface_GLA": ["2625"], "Mobile": ["+ 3 93 35 27 75 93"]}
{"Fonction": ["Responsable commercialisation"], "Ville": ["HAGUENAU"], "Surface_hyper": ["10000"], "Statut": ["Ouvert"], "Telephone": ["01.77.51.00.69"], "Site": ["Schweighouse"], "Mail": ["ngauthier@immochan.com"], "Nb_boutiques": ["23"], "Contact": ["Nathalie GAUTHIER"], "Surface_GLA": ["2700"], "Mobile": ["06.23.34.44.40"]}
{"Fonction": ["Responsable Commercialisation Aquarelle"], "Ville": ["Volgograd"], "Surface_hyper": [], "Statut": ["Ouvert"], "Telephone": ["+7 (903) 665 07 48"], "Site": ["АКВАРЕЛЬ"], "Mail": ["m.rakova@auchan.ru"], "Nb_boutiques": ["184"], "Contact": ["Viktoria ZAITSEVA"], "Surface_GLA": ["94035"], "Mobile": []}
{"Fonction": ["Chef de Projet"], "Ville": ["région de Moscou"], "Surface_hyper": ["22480"], "Statut": ["Nouveaux projets"], "Telephone": [" +7 (495) 724 10 10"], "Site": ["Pushkino"], "Mail": ["ir.alieva@auchan.ru"], "Nb_boutiques": ["100"], "Contact": ["Irada ALIEVA"], "Surface_GLA": ["48600"], "Mobile": ["+7 (903) 665 97 46 "]}
{"Fonction": ["Directrice régionale des centres commerciaux"], "Ville": ["Shanghai "], "Surface_hyper": ["8000"], "Statut": ["Ouvert"], "Telephone": ["+ (86) 021 25 05 21 32"], "Site": ["Shanghai Jiading"], "Mail": ["hui.fan@auchan.com.cn"], "Nb_boutiques": ["19"], "Contact": ["Hui FAN"], "Surface_GLA": ["1015"], "Mobile": []}
{"Fonction": ["Responsable commercialisation"], "Ville": ["STRASBOURG"], "Surface_hyper": ["9740"], "Statut": ["Ouvert"], "Telephone": ["01.77.51.00.69"], "Site": ["Strasbourg Hautepierre "], "Mail": ["ngauthier@immochan.com"], "Nb_boutiques": ["52"], "Contact": ["Nathalie GAUTHIER"], "Surface_GLA": ["12410"], "Mobile": ["06.23.34.44.40"]}
{"Fonction": ["Directeur Commercial"], "Ville": ["Budapest"], "Surface_hyper": ["15493"], "Statut": ["Extension - Rénovation"], "Telephone": [], "Site": ["Soroksár"], "Mail": [""], "Nb_boutiques": ["64"], "Contact": ["Gábosy Balázs"], "Surface_GLA": ["6076"], "Mobile": []}
{"Fonction": ["Directrice régionale des centres commerciaux"], "Ville": ["Shanghai"], "Surface_hyper": ["11424"], "Statut": ["Ouvert"], "Telephone": ["+ (86) 021 25 05 21 32"], "Site": ["Shanghai Zhongyan YP2"], "Mail": ["hui.fan@auchan.com.cn"], "Nb_boutiques": ["46"], "Contact": ["Hui FAN"], "Surface_GLA": ["2848"], "Mobile": []}
{"Fonction": ["Responsable de commercialisation"], "Ville": ["Solymár"], "Surface_hyper": ["11867"], "Statut": ["Ouvert"], "Telephone": ["+ 36 18 87 45 42"], "Site": ["Solymár"], "Mail": ["t.zacharilles@auchan.hu"], "Nb_boutiques": ["22"], "Contact": ["Tamás ZACHAR ILLÉS"], "Surface_GLA": ["1936"], "Mobile": ["+ 363 02 74 56 49"]}
{"Fonction": ["Responsable commercialisation"], "Ville": ["ILLKIRCH GRAFFENSTADEN"], "Surface_hyper": ["14300"], "Statut": ["Ouvert"], "Telephone": ["01.77.51.00.69"], "Site": ["Strasbourg Illkirch "], "Mail": ["ngauthier@immochan.com"], "Nb_boutiques": ["69"], "Contact": ["Nathalie GAUTHIER"], "Surface_GLA": ["15600"], "Mobile": ["06.23.34.44.40"]}
{"Fonction": ["Responsable de commercialisation"], "Ville": ["SIBIU"], "Surface_hyper": ["6100"], "Statut": ["Ouvert"], "Telephone": [], "Site": ["Sibiu"], "Mail": ["ampop@immochan.com"], "Nb_boutiques": ["17"], "Contact": ["Anca Pop"], "Surface_GLA": ["931"], "Mobile": ["+ 40 748 05 12 74"]}
{"Fonction": ["Directrice régionale des centres commerciaux"], "Ville": ["Shanghai "], "Surface_hyper": ["8870"], "Statut": ["Ouvert"], "Telephone": ["+ (86) 021 25 05 21 32"], "Site": ["Shanghai Minhang"], "Mail": ["hui.fan@auchan.com.cn"], "Nb_boutiques": ["46"], "Contact": ["Hui FAN"], "Surface_GLA": ["2460"], "Mobile": []}
{"Fonction": ["Directrice régionale des centres commerciaux"], "Ville": ["Shanghai"], "Surface_hyper": ["9133"], "Statut": ["Ouvert"], "Telephone": ["+ (86) 021 25 05 21 32"], "Site": ["Shanghai Nanhui"], "Mail": ["hui.fan@auchan.com.cn"], "Nb_boutiques": ["70"], "Contact": ["Hui FAN"], "Surface_GLA": ["6280"], "Mobile": []}
{"Fonction": ["Directrice régionale des centres commerciaux"], "Ville": ["Shanghai"], "Surface_hyper": ["10080"], "Statut": ["Ouvert"], "Telephone": ["+ (86) 021 25 05 21 32"], "Site": ["Shanghai Jinshan"], "Mail": ["hui.fan@auchan.com.cn"], "Nb_boutiques": ["58"], "Contact": ["Hui FAN"], "Surface_GLA": ["5279"], "Mobile": []}
{"Fonction": ["Directeur Commercialisation centres commerciaux"], "Ville": ["Shanghai"], "Surface_hyper": ["18000"], "Statut": ["Ouvert"], "Telephone": [], "Site": ["Sun Art Plaza"], "Mail": [""], "Nb_boutiques": ["150"], "Contact": ["Liu ZHIJUN"], "Surface_GLA": ["41000"], "Mobile": []}
{"Fonction": ["Responsable Commercialisation Region de Moscou"], "Ville": ["Moscou"], "Surface_hyper": [], "Statut": ["Ouvert"], "Telephone": ["+7 (903) 665 10 39"], "Site": ["ТРОЙКА"], "Mail": ["i.palaguina@auchan.ru"], "Nb_boutiques": ["109"], "Contact": ["Irina PALAGUINA"], "Surface_GLA": ["60799"], "Mobile": []}
{"Fonction": ["Responsable Galeries Marchandes"], "Ville": ["Tainan"], "Surface_hyper": ["8527"], "Statut": ["Ouvert"], "Telephone": ["+ 88 82 27 95 28 88"], "Site": ["Tainan"], "Mail": ["ga07@rt-mart.com.tw"], "Nb_boutiques": ["24"], "Contact": ["Roman LEE"], "Surface_GLA": ["6007"], "Mobile": []}
{"Fonction": ["Responsable de commercialisation"], "Ville": ["Szigetszentmiklós"], "Surface_hyper": ["14382"], "Statut": ["Ouvert"], "Telephone": ["+ 36 18 87 45 33"], "Site": ["Szigetszentmiklós"], "Mail": ["o.baki@auchan.hu"], "Nb_boutiques": ["26"], "Contact": ["Orsolya BAKI"], "Surface_GLA": ["1814"], "Mobile": ["+ 363 02 51 94 09"]}
{"Fonction": ["Responsable Galeries Marchandes"], "Ville": ["Taitung"], "Surface_hyper": ["5914"], "Statut": ["Ouvert"], "Telephone": ["+ 88 82 27 95 28 88"], "Site": ["Taitung"], "Mail": ["ga06@rt-mart.com.tw"], "Nb_boutiques": ["8"], "Contact": ["Pat HO"], "Surface_GLA": ["591"], "Mobile": []}
{"Fonction": ["Responsable commercialisation"], "Ville": ["Taranto"], "Surface_hyper": ["7540"], "Statut": ["Extension - Rénovation"], "Telephone": ["+39 02 57 58 48 64"], "Site": ["Taranto"], "Mail": ["giampiero.dimaio@gcispa.com"], "Nb_boutiques": ["51"], "Contact": ["Giampiero DI MAIO"], "Surface_GLA": ["11753"], "Mobile": []}
{"Fonction": ["Directeur Commercial"], "Ville": ["Szolnok"], "Surface_hyper": ["8615"], "Statut": ["Extension - Rénovation"], "Telephone": [], "Site": ["Szolnok"], "Mail": [""], "Nb_boutiques": ["24"], "Contact": ["Gábosy Balázs"], "Surface_GLA": ["1572"], "Mobile": []}
{"Fonction": ["Responsable de commercialisation"], "Ville": ["Székesfehérvár"], "Surface_hyper": ["12555"], "Statut": ["Ouvert"], "Telephone": [], "Site": ["Székesfehérvár"], "Mail": [], "Nb_boutiques": ["21"], "Contact": [], "Surface_GLA": ["1462"], "Mobile": []}
{"Fonction": ["Responsable de commercialisation"], "Ville": ["Szeged"], "Surface_hyper": ["10940"], "Statut": ["Ouvert"], "Telephone": [], "Site": ["Szeged"], "Mail": [], "Nb_boutiques": ["25"], "Contact": [], "Surface_GLA": ["3477"], "Mobile": []}
{"Fonction": ["Directeur régional des centres commerciaux"], "Ville": ["Suzhou"], "Surface_hyper": ["17000"], "Statut": ["Ouvert"], "Telephone": [], "Site": ["Suzhou jinjihu"], "Mail": ["honghui.zhou@auchan.com.cn"], "Nb_boutiques": ["132"], "Contact": ["Honghui ZHOU"], "Surface_GLA": ["22952"], "Mobile": []}
{"Fonction": ["Responsable Galeries Marchandes"], "Ville": ["TELDE -  GRAN CANARIA"], "Surface_hyper": ["11303"], "Statut": ["Ouvert"], "Telephone": ["+ 34 91 730 66 66"], "Site": ["TELDE"], "Mail": ["jc.garcia@alcampo.es"], "Nb_boutiques": ["28"], "Contact": ["José Carlos GARCIA"], "Surface_GLA": ["3136"], "Mobile": ["+ 34 606 432 723"]}
{"Fonction": ["Responsable commercialisation"], "Ville": ["FONTENAY- SOUS - BOIS "], "Surface_hyper": ["13500"], "Statut": ["Ouvert"], "Telephone": [], "Site": ["Val Fontenay"], "Mail": ["sauneau@immochan.com"], "Nb_boutiques": ["91"], "Contact": ["Stéphanie Auneau"], "Surface_GLA": ["21972"], "Mobile": ["06.72.04.66.89"]}
{"Fonction": ["Responsable Galeries Marchandes"], "Ville": ["UTEBO - ZARAGOZA"], "Surface_hyper": ["10428"], "Statut": ["Ouvert"], "Telephone": ["+ 34 91 730 66 66"], "Site": ["UTEBO"], "Mail": ["lf.ubeda@alcampo.es"], "Nb_boutiques": ["25"], "Contact": ["Luis UBEDA"], "Surface_GLA": ["2482"], "Mobile": ["+ 34 629 858 392"]}
{"Fonction": ["Responsable Galeries Marchandes"], "Ville": ["New Taipei"], "Surface_hyper": ["9004"], "Statut": ["Ouvert"], "Telephone": ["+ 88 82 27 95 28 88"], "Site": ["Tucheng"], "Mail": ["ga08@rt-mart.com.tw"], "Nb_boutiques": ["17"], "Contact": ["Rick HSU"], "Surface_GLA": ["720"], "Mobile": []}
{"Fonction": ["Responsable de commercialisation"], "Ville": ["Törökbálint"], "Surface_hyper": ["12667"], "Statut": ["Ouvert"], "Telephone": ["+ 36 18 87 45 42"], "Site": ["Törökbálint"], "Mail": ["t.zacharilles@auchan.hu"], "Nb_boutiques": ["47"], "Contact": ["Tamás ZACHAR ILLÉS"], "Surface_GLA": ["71245"], "Mobile": ["+ 363 02 74 56 49"]}
{"Fonction": ["Responsable Galeries Marchandes"], "Ville": ["Tounan Town, Comté de Win lin"], "Surface_hyper": ["6592"], "Statut": ["Ouvert"], "Telephone": ["+ 88 82 27 95 28 88"], "Site": ["Tounan"], "Mail": ["ga07@rt-mart.com.tw"], "Nb_boutiques": ["15"], "Contact": ["Roman LEE"], "Surface_GLA": ["457"], "Mobile": []}
{"Fonction": ["Directeur de commercialisation"], "Ville": ["Torino"], "Surface_hyper": ["9760"], "Statut": ["Extension - Rénovation"], "Telephone": ["+39 02 57 58 48 64"], "Site": ["Torino"], "Mail": ["giampiero.dimaio@gcispa.com"], "Nb_boutiques": ["37"], "Contact": ["Giampiero DI MAIO"], "Surface_GLA": ["5673"], "Mobile": []}
{"Fonction": ["Responsable Galeries Marchandes"], "Ville": ["Taichung 404"], "Surface_hyper": ["10616"], "Statut": ["Ouvert"], "Telephone": ["+ 88 82 27 95 28 88"], "Site": ["Tofen"], "Mail": ["ga08@rt-mart.com.tw"], "Nb_boutiques": ["25"], "Contact": ["Rick HSU"], "Surface_GLA": ["1869"], "Mobile": []}
{"Fonction": ["Directeur Commercial"], "Ville": ["BUCAREST"], "Surface_hyper": ["16000"], "Statut": ["Ouvert"], "Telephone": [], "Site": ["Titan "], "Mail": [], "Nb_boutiques": ["67"], "Contact": [], "Surface_GLA": ["7315"], "Mobile": []}
{"Fonction": ["Leasing Manager"], "Ville": ["Tîrgu Mureș"], "Surface_hyper": ["6000"], "Statut": ["Ouvert"], "Telephone": [], "Site": ["TÎRGU MUREȘ"], "Mail": ["ampop@immochan.com"], "Nb_boutiques": ["33"], "Contact": ["Anca Pop"], "Surface_GLA": ["4025"], "Mobile": ["+ 40 748 05 12 74"]}
{"Fonction": ["Responsable commercialisation"], "Ville": ["VALENCE"], "Surface_hyper": ["9250"], "Statut": ["Extension - Rénovation"], "Telephone": [], "Site": ["Valence Guilherand Granges"], "Mail": ["amiel@immochan.com"], "Nb_boutiques": ["51"], "Contact": ["Aurore MIEL"], "Surface_GLA": ["8394"], "Mobile": ["06.46.15.75.09"]}
{"Fonction": ["Responsable commercialisation"], "Ville": ["VILLARS"], "Surface_hyper": ["12195"], "Statut": ["Ouvert"], "Telephone": ["04 13 60 06 07"], "Site": ["Villars"], "Mail": ["dbenisty@immochan.com"], "Nb_boutiques": ["55"], "Contact": ["Delphine BENISTY"], "Surface_GLA": ["5615"], "Mobile": ["06 03 23 39 64"]}
{"Fonction": ["Responsable Galeries Marchandes"], "Ville": ["VIGO - PONTEVEDRA"], "Surface_hyper": ["8106"], "Statut": ["Ouvert"], "Telephone": ["+ 34 91 730 66 66"], "Site": ["VIGO 1"], "Mail": ["angel.garcia@alcampo.es"], "Nb_boutiques": ["9"], "Contact": ["Angel GARCIA"], "Surface_GLA": ["1013"], "Mobile": ["+ 34 618 342 095"]}
{"Fonction": ["Responsable  commercialisation"], "Ville": ["VILLEBON SUR YVETTE"], "Surface_hyper": ["10300"], "Statut": ["Extension - Rénovation"], "Telephone": ["01 47 62 61 68"], "Site": ["Villebon/Yvette "], "Mail": ["fmoreau@immochan.com"], "Nb_boutiques": ["20"], "Contact": ["Frédérike  MOREAU"], "Surface_GLA": ["2033"], "Mobile": ["06 29 75 75 17"]}
{"Fonction": ["Responsable Galeries Marchandes"], "Ville": ["VIGO - PONTEVEDRA"], "Surface_hyper": ["8658"], "Statut": ["Ouvert"], "Telephone": ["+ 34 91 730 66 66"], "Site": ["VIGO 2"], "Mail": ["angel.garcia@alcampo.es"], "Nb_boutiques": ["17"], "Contact": ["Angel GARCIA"], "Surface_GLA": ["1322"], "Mobile": ["+ 34 618 342 095"]}
{"Fonction": ["Directeur de commercialisation"], "Ville": ["Venaria"], "Surface_hyper": ["9435"], "Statut": ["Ouvert"], "Telephone": ["+39 02 57 58 48 64"], "Site": ["Venaria"], "Mail": ["giampiero.dimaio@gcispa.com"], "Nb_boutiques": ["23"], "Contact": ["Giampiero DI MAIO"], "Surface_GLA": ["5993"], "Mobile": []}
{"Fonction": ["Directeur de commercialisation"], "Ville": ["Vicenza"], "Surface_hyper": ["7575"], "Statut": ["Ouvert"], "Telephone": ["+39 02 57 58 48 64"], "Site": ["Vicenza"], "Mail": ["giampiero.dimaio@gcispa.com"], "Nb_boutiques": ["9"], "Contact": ["Giampiero DI MAIO"], "Surface_GLA": ["1959"], "Mobile": []}
{"Fonction": ["Responsable Galeries Marchandes"], "Ville": ["MADRID"], "Surface_hyper": ["7106"], "Statut": ["Ouvert"], "Telephone": ["+ 34 91 730 66 66"], "Site": ["VALLECAS"], "Mail": ["angel.garcia@alcampo.es"], "Nb_boutiques": ["10"], "Contact": ["Angel GARCIA"], "Surface_GLA": ["328"], "Mobile": ["+ 34 618 342 095"]}
{"Fonction": ["Responsable  commercialisation"], "Ville": ["VALENCIENNES"], "Surface_hyper": ["7000"], "Statut": ["Ouvert"], "Telephone": ["03.62.53.79.41"], "Site": ["Valenciennes"], "Mail": ["arousselot-doisy@immochan.com"], "Nb_boutiques": ["9"], "Contact": ["Angélique ROUSSELOT-DOISY"], "Surface_GLA": ["930"], "Mobile": ["06.62.13.63.39"]}
{"Fonction": ["Responsable Galeries Marchandes"], "Ville": ["EL ENTREGO - ASTURIAS"], "Surface_hyper": ["8685"], "Statut": ["Ouvert"], "Telephone": ["+ 34 91 730 66 66"], "Site": ["VALLE DEL NALÓN"], "Mail": ["p.gomez-peralta@alcampo.es"], "Nb_boutiques": ["61"], "Contact": ["Pablo GOMEZ"], "Surface_GLA": ["14176"], "Mobile": ["+ 34 669 502 976"]}
{"Fonction": ["Directeur de commercialisation"], "Ville": ["Vimodrone"], "Surface_hyper": ["10255"], "Statut": ["Ouvert"], "Telephone": ["+39 02 57 58 48 64"], "Site": ["Vimodrone"], "Mail": ["giampiero.dimaio@gcispa.com"], "Nb_boutiques": ["54"], "Contact": ["Giampiero DI MAIO"], "Surface_GLA": ["10036"], "Mobile": []}
{"Fonction": ["Directrice Commerciale Espagne"], "Ville": ["ORIHUELA COSTA - ALICANTE"], "Surface_hyper": ["14000"], "Statut": ["Ouvert"], "Telephone": [], "Site": ["ZENIA BOULEVARD "], "Mail": [], "Nb_boutiques": ["148"], "Contact": [], "Surface_GLA": ["67682"], "Mobile": []}
{"Fonction": ["Directrice régionale des centres commerciaux"], "Ville": ["Yangzhou"], "Surface_hyper": ["9520"], "Statut": ["Ouvert"], "Telephone": ["+ (86) 021 25 05 21 32"], "Site": ["Yangzhou Jiangyang"], "Mail": ["hui.fan@auchan.com.cn"], "Nb_boutiques": ["65"], "Contact": ["Hui FAN"], "Surface_GLA": ["6245"], "Mobile": []}
{"Fonction": ["Directeur régional des centres commerciaux"], "Ville": ["Wuxi"], "Surface_hyper": ["9337"], "Statut": ["Ouvert"], "Telephone": [], "Site": ["Wuxi 2 Lihu"], "Mail": ["honghui.zhou@auchan.com.cn"], "Nb_boutiques": ["71"], "Contact": ["Honghui ZHOU"], "Surface_GLA": ["6410"], "Mobile": []}
{"Fonction": ["Responsable Galeries Marchandes"], "Ville": ["Comté de Changhua"], "Surface_hyper": ["8521"], "Statut": ["Ouvert"], "Telephone": ["+ 88 82 27 95 28 88"], "Site": ["Yuanlin"], "Mail": ["ga07@rt-mart.com.tw"], "Nb_boutiques": ["38"], "Contact": ["Roman LEE"], "Surface_GLA": ["1899"], "Mobile": []}
{"Fonction": ["Responsable Galeries Marchandes"], "Ville": ["ZARAGOZA"], "Surface_hyper": ["10981"], "Statut": ["Ouvert"], "Telephone": ["+ 34 91 730 66 66"], "Site": ["ZARAGOZA 2"], "Mail": ["lf.ubeda@alcampo.es"], "Nb_boutiques": ["22"], "Contact": ["Luis UBEDA"], "Surface_GLA": ["4287"], "Mobile": ["+ 34 629 858 392"]}
{"Fonction": ["Directrice régionale des centres commerciaux"], "Ville": ["Wuhu"], "Surface_hyper": ["9182"], "Statut": ["Ouvert"], "Telephone": ["+ (86) 021 25 05 21 32"], "Site": ["Wuhu 2 Huajiang"], "Mail": ["hui.fan@auchan.com.cn"], "Nb_boutiques": ["51"], "Contact": ["Hui FAN"], "Surface_GLA": ["4862"], "Mobile": []}
{"Fonction": ["Directrice régionale des centres commerciaux"], "Ville": ["Wuhu"], "Surface_hyper": ["9300"], "Statut": ["Ouvert"], "Telephone": ["+ (86) 021 25 05 21 32"], "Site": ["Wuhu 1 Tianmenshanlu"], "Mail": ["hui.fan@auchan.com.cn"], "Nb_boutiques": ["52"], "Contact": ["Hui FAN"], "Surface_GLA": ["4767"], "Mobile": []}
{"Fonction": ["Responsable commercialisation"], "Ville": ["Nola"], "Surface_hyper": ["13365"], "Statut": ["Ouvert"], "Telephone": ["+ (02) 57 58 21 10"], "Site": ["Vulcano Buono"], "Mail": ["ettore.papponetti@gcispa.com"], "Nb_boutiques": ["156"], "Contact": ["Ettore PAPPONETTI"], "Surface_GLA": ["60442"], "Mobile": ["+ 3 93 35 27 75 93"]}
{"Fonction": ["Responsable de commercialisation"], "Ville": ["BUCAREST"], "Surface_hyper": ["6100"], "Statut": ["Ouvert"], "Telephone": [], "Site": ["Vitan"], "Mail": ["ampop@immochan.com"], "Nb_boutiques": ["18"], "Contact": ["Anca Pop"], "Surface_GLA": ["2671"], "Mobile": ["+ 40 748 05 12 74"]}
{"Fonction": ["Directrice régionale des centres commerciaux"], "Ville": ["Zhengjiang"], "Surface_hyper": ["10141"], "Statut": ["Ouvert"], "Telephone": ["+ (86) 021 25 05 21 32"], "Site": ["Zhenjiang Xuefu"], "Mail": ["hui.fan@auchan.com.cn"], "Nb_boutiques": ["62"], "Contact": ["Hui FAN"], "Surface_GLA": ["6533"], "Mobile": []}
{"Fonction": ["Chef de projet"], "Ville": ["Togliatti"], "Surface_hyper": ["13540"], "Statut": ["Nouveaux projets"], "Telephone": [" +7 (495) 724 10 10"], "Site": ["Togliatti"], "Mail": ["ir.alieva@auchan.ru"], "Nb_boutiques": ["54"], "Contact": ["Irada ALIEVA"], "Surface_GLA": ["11600"], "Mobile": ["+7 (903) 665 97 46 "]}
{"Fonction": ["Directrice régionale des centres commerciaux"], "Ville": ["Zhoushan, Zhejiang"], "Surface_hyper": ["7801"], "Statut": ["Ouvert"], "Telephone": ["+ (86) 021 25 05 21 32"], "Site": ["Zhoushan"], "Mail": ["hui.fan@auchan.com.cn"], "Nb_boutiques": ["45"], "Contact": ["Hui FAN"], "Surface_GLA": ["2726"], "Mobile": []}
{"Fonction": ["Responsable développement"], "Ville": ["Moscou"], "Surface_hyper": ["11604"], "Statut": ["Nouveaux projets"], "Telephone": [" +7 (495) 724 10 10"], "Site": ["Proletarsky"], "Mail": ["ir.alieva@auchan.ru"], "Nb_boutiques": ["36"], "Contact": ["Irada ALIEVA"], "Surface_GLA": ["3857"], "Mobile": ["+7 (903) 665 97 46 "]}
